[{"id":1,"Nombre":"Araracuara Airport","code":"ACR","region-code":"CO-CAQ","continente":"SA"},
{"id":2,"Nombre":"Shaw Air Force Base","code":"SSC","region-code":"US-SC","continente":"NA"},
{"id":3,"Nombre":"Mariupol International Airport","code":"MPW","region-code":"UA-14","continente":"EU"},
{"id":4,"Nombre":"Governor's Harbour Airport","code":"GHB","region-code":"BS-GH","continente":"NA"},
{"id":5,"Nombre":"Teuku Cut Ali Airport","code":"TPK","region-code":"ID-AC","continente":"AS"},
{"id":6,"Nombre":"General Villamil Airport","code":"IBB","region-code":"EC-W","continente":"SA"},
{"id":7,"Nombre":"El Dorado Airport","code":"EOR","region-code":"VE-F","continente":"SA"},
{"id":8,"Nombre":"Bakkafjörður Airport","code":"BJD","region-code":"IS-6","continente":"EU"},
{"id":9,"Nombre":"Babo Airport","code":"BXB","region-code":"ID-PB","continente":"AS"},
{"id":10,"Nombre":"Moose Jaw Air Vice Marshal C. M. McEwen Airport","code":"YMJ","region-code":"CA-SK","continente":"NA"},
{"id":11,"Nombre":"Lashio Airport","code":"LSH","region-code":"MM-17","continente":"AS"},
{"id":12,"Nombre":"Pulau Panjang Airport","code":"PPJ","region-code":"ID-JB","continente":"AS"},
{"id":13,"Nombre":"Canton Island Airport","code":"CIS","region-code":"KI-P","continente":"OC"},
{"id":14,"Nombre":"Daocheng Yading Airport","code":"DCY","region-code":"CN-51","continente":"AS"},
{"id":15,"Nombre":"Headingly Airport","code":"HIP","region-code":"AU-QLD","continente":"OC"},
{"id":16,"Nombre":"Goya Airport","code":"OYA","region-code":"AR-W","continente":"SA"},
{"id":17,"Nombre":"Faya Largeau Airport","code":"FYT","region-code":"TD-BET","continente":"AF"},
{"id":18,"Nombre":"Bremerhaven Airport","code":"BRV","region-code":"DE-HB","continente":"EU"},
{"id":19,"Nombre":"Kilaguni Airport","code":"ILU","region-code":"KE-300","continente":"AF"},
{"id":20,"Nombre":"Grand Central Airport","code":"GCJ","region-code":"ZA-GT","continente":"AF"},
{"id":21,"Nombre":"Angoon Seaplane Base","code":"AGN","region-code":"US-AK","continente":"NA"},
{"id":22,"Nombre":"Oum el Bouaghi airport","code":"QMH","region-code":"DZ-04","continente":"AF"},
{"id":23,"Nombre":"Heho Airport","code":"HEH","region-code":"MM-17","continente":"AS"},
{"id":24,"Nombre":"Bykovo Airport","code":"BKA","region-code":"RU-MOS","continente":"EU"},
{"id":25,"Nombre":"Sasstown Airport","code":"SAZ","region-code":"LR-GK","continente":"AF"},
{"id":26,"Nombre":"Argyle Airport","code":"GYL","region-code":"AU-WA","continente":"OC"},
{"id":27,"Nombre":"Cherkasy International Airport","code":"CKC","region-code":"UA-71","continente":"EU"},
{"id":28,"Nombre":"Mundo Maya International Airport","code":"FRS","region-code":"GT-PE","continente":"NA"},
{"id":29,"Nombre":"Skardu Airport","code":"KDU","region-code":"PK-NA","continente":"AS"},
{"id":30,"Nombre":"Oconee County Regional Airport","code":"CEU","region-code":"US-SC","continente":"NA"},
{"id":31,"Nombre":"Maribor Airport","code":"MBX","region-code":"SI-070","continente":"EU"},
{"id":32,"Nombre":"Mzuzu Airport","code":"ZZU","region-code":"MW-MZ","continente":"AF"},
{"id":33,"Nombre":"Seward Airport","code":"SWD","region-code":"US-AK","continente":"NA"},
{"id":34,"Nombre":"Badu Island Airport","code":"BDD","region-code":"AU-QLD","continente":"OC"},
{"id":35,"Nombre":"Easterwood Field","code":"CLL","region-code":"US-TX","continente":"NA"},
{"id":36,"Nombre":"Aberdeen Dyce Airport","code":"ABZ","region-code":"GB-SCT","continente":"EU"},
{"id":37,"Nombre":"Kristiansand Airport","code":"KRS","region-code":"NO-10","continente":"EU"},
{"id":38,"Nombre":"Bull Harbour Water Aerodrome","code":"YBH","region-code":"CA-BC","continente":"NA"},
{"id":39,"Nombre":"Milano Linate Airport","code":"LIN","region-code":"IT-25","continente":"EU"},
{"id":40,"Nombre":"Matsapha Airport","code":"MTS","region-code":"SZ-MA","continente":"AF"},
{"id":41,"Nombre":"San Sebastian Airport","code":"EAS","region-code":"ES-PV","continente":"EU"},
{"id":42,"Nombre":"Toledo Airport","code":"TOW","region-code":"BR-PR","continente":"SA"},
{"id":43,"Nombre":"Pécs-Pogány Airport","code":"PEV","region-code":"HU-BA","continente":"EU"},
{"id":44,"Nombre":"Morehead Airport","code":"MHY","region-code":"PG-WPD","continente":"OC"},
{"id":45,"Nombre":"Thandwe Airport","code":"SNW","region-code":"MM-16","continente":"AS"},
{"id":46,"Nombre":"Range Regional Airport","code":"HIB","region-code":"US-MN","continente":"NA"},
{"id":47,"Nombre":"Piloto Osvaldo Marques Dias Airport","code":"AFL","region-code":"BR-MT","continente":"SA"},
{"id":48,"Nombre":"Los Colonizadores Airport","code":"RVE","region-code":"CO-ARA","continente":"SA"},
{"id":49,"Nombre":"York Landing Airport","code":"ZAC","region-code":"CA-MB","continente":"NA"},
{"id":50,"Nombre":"Mohamed Boudiaf International Airport","code":"CZL","region-code":"DZ-25","continente":"AF"},
{"id":51,"Nombre":"Alberto Delgado Airport","code":"TND","region-code":"CU-07","continente":"NA"},
{"id":52,"Nombre":"Fritzlar Airport","code":"FRZ","region-code":"DE-HE","continente":"EU"},
{"id":53,"Nombre":"Stroudsburg Pocono Airport","code":"ESP","region-code":"US-PA","continente":"NA"},
{"id":54,"Nombre":"Duke Field","code":"EGI","region-code":"US-FL","continente":"NA"},
{"id":55,"Nombre":"Žabljak Airport","code":"ZBK","region-code":"ME-21","continente":"EU"},
{"id":56,"Nombre":"Tarama Airport","code":"TRA","region-code":"JP-47","continente":"AS"},
{"id":57,"Nombre":"Likiep Airport","code":"LIK","region-code":"MH-LIK","continente":"OC"},
{"id":58,"Nombre":"Teslin Airport","code":"YZW","region-code":"CA-YT","continente":"NA"},
{"id":59,"Nombre":"Tambor Airport","code":"TMU","region-code":"CR-P","continente":"NA"},
{"id":60,"Nombre":"Damazin Airport","code":"RSS","region-code":"SD-24","continente":"AF"},
{"id":61,"Nombre":"Paso Caballos Airport","code":"PCG","region-code":"GT-PE","continente":"NA"},
{"id":62,"Nombre":"Mário de Almeida Franco Airport","code":"UBA","region-code":"BR-MG","continente":"SA"},
{"id":63,"Nombre":"Jequié Airport","code":"JEQ","region-code":"BR-BA","continente":"SA"},
{"id":64,"Nombre":"Fort Sumner Municipal Airport","code":"FSU","region-code":"US-NM","continente":"NA"},
{"id":65,"Nombre":"Devils Lake Regional Airport","code":"DVL","region-code":"US-ND","continente":"NA"},
{"id":66,"Nombre":"Bolwarra Airport","code":"BCK","region-code":"AU-QLD","continente":"OC"},
{"id":67,"Nombre":"Hopedale Airport","code":"YHO","region-code":"CA-NL","continente":"NA"},
{"id":68,"Nombre":"Gasuke Airport","code":"GBC","region-code":"PG-WPD","continente":"OC"},
{"id":69,"Nombre":"Cochstedt Airport","code":"CSO","region-code":"DE-ST","continente":"EU"},
{"id":70,"Nombre":"Mayaguana Airport","code":"MYG","region-code":"BS-MG","continente":"NA"},
{"id":71,"Nombre":"Dr. Arturo H. Illia Airport","code":"GNR","region-code":"AR-R","continente":"SA"},
{"id":72,"Nombre":"Savoonga Airport","code":"SVA","region-code":"US-AK","continente":"NA"},
{"id":73,"Nombre":"Angel Albino Corzo International Airport","code":"TGZ","region-code":"MX-CHP","continente":"NA"},
{"id":74,"Nombre":"Eil Airport","code":"HCM","region-code":"SO-NU","continente":"AF"},
{"id":75,"Nombre":"Antalya International Airport","code":"AYT","region-code":"TR-07","continente":"AS"},
{"id":76,"Nombre":"Indigo Bay Lodge Airport","code":"IBL","region-code":"MZ-I","continente":"AF"},
{"id":77,"Nombre":"Urad Middle Banner","code":"WZQ","region-code":"CN-15","continente":"AS"},
{"id":78,"Nombre":"Suria Airport","code":"SUZ","region-code":"PG-CPM","continente":"OC"},
{"id":79,"Nombre":"George R Carr Memorial Air Field","code":"BXA","region-code":"US-LA","continente":"NA"},
{"id":80,"Nombre":"Dr. Antonio Nicolás Briceño Airport","code":"VLV","region-code":"VE-T","continente":"SA"},
{"id":81,"Nombre":"Tambao Airport","code":"TMQ","region-code":"BF-OUD","continente":"AF"},
{"id":82,"Nombre":"Sumbe Airport","code":"NDD","region-code":"AO-CUS","continente":"AF"},
{"id":83,"Nombre":"Choiseul Bay Airport","code":"CHY","region-code":"SB-CH","continente":"OC"},
{"id":84,"Nombre":"Union Island International Airport","code":"UNI","region-code":"VC-06","continente":"NA"},
{"id":85,"Nombre":"Hangzhou Xiaoshan International Airport","code":"HGH","region-code":"CN-33","continente":"AS"},
{"id":86,"Nombre":"Poplar River Airport","code":"XPP","region-code":"CA-MB","continente":"NA"},
{"id":87,"Nombre":"Alashankou Bole (Bortala) airport","code":"BPL","region-code":"CN-65","continente":"AS"},
{"id":88,"Nombre":"Belbek Airport","code":"UKS","region-code":"UA-43","continente":"EU"},
{"id":89,"Nombre":"Cesar Lim Rodriguez Airport","code":"RZP","region-code":"PH-PLW","continente":"AS"},
{"id":90,"Nombre":"Mayo Airport","code":"YMA","region-code":"CA-YT","continente":"NA"},
{"id":91,"Nombre":"King Abdulaziz Air Base","code":"DHA","region-code":"SA-04","continente":"AS"},
{"id":92,"Nombre":"Singapore Changi Airport","code":"SIN","region-code":"SG-04","continente":"AS"},
{"id":93,"Nombre":"Moucha Airport","code":"MHI","region-code":"DJ-DJ","continente":"AF"},
{"id":94,"Nombre":"Porter County Municipal Airport","code":"VPZ","region-code":"US-IN","continente":"NA"},
{"id":95,"Nombre":"V.C. Bird International Airport","code":"ANU","region-code":"AG-03","continente":"NA"},
{"id":96,"Nombre":"Batajnica Air Base","code":"BJY","region-code":"RS-07","continente":"EU"},
{"id":97,"Nombre":"Luena Airport","code":"LUO","region-code":"AO-MOX","continente":"AF"},
{"id":98,"Nombre":"Polyarny Airport","code":"PYJ","region-code":"RU-SA","continente":"AS"},
{"id":99,"Nombre":"Alzintan Airport","code":"ZIS","region-code":"LY-JG","continente":"AF"},
{"id":100,"Nombre":"Ernabella Airport","code":"ERB","region-code":"AU-SA","continente":"OC"},
{"id":101,"Nombre":"Martin State Airport","code":"MTN","region-code":"US-MD","continente":"NA"},
{"id":102,"Nombre":"Morichal Airport","code":"MHF","region-code":"CO-VAU","continente":"SA"},
{"id":103,"Nombre":"Rio Amazonas Airport","code":"PTZ","region-code":"EC-Y","continente":"SA"},
{"id":104,"Nombre":"Cochin International Airport","code":"COK","region-code":"IN-KL","continente":"AS"},
{"id":105,"Nombre":"L.F. Wade International International Airport","code":"BDA","region-code":"BM-U-A","continente":"NA"},
{"id":106,"Nombre":"Bay City Municipal Airport","code":"BBC","region-code":"US-TX","continente":"NA"},
{"id":107,"Nombre":"Eqalugaarsuit Heliport","code":"QFG","region-code":"GL-U-A","continente":"NA"},
{"id":108,"Nombre":"Degah Bur Airport","code":"DGC","region-code":"ET-SO","continente":"AF"},
{"id":109,"Nombre":"Canton Municipal Airport","code":"CTK","region-code":"US-SD","continente":"NA"},
{"id":110,"Nombre":"Leonora Airport","code":"LNO","region-code":"AU-WA","continente":"OC"},
{"id":111,"Nombre":"Einasleigh Airport","code":"EIH","region-code":"AU-QLD","continente":"OC"},
{"id":112,"Nombre":"Palma Airport","code":"LMZ","region-code":"MZ-P","continente":"AF"},
{"id":113,"Nombre":"Blackbushe Airport","code":"BBS","region-code":"GB-ENG","continente":"EU"},
{"id":114,"Nombre":"Thompson Airport","code":"YTH","region-code":"CA-MB","continente":"NA"},
{"id":115,"Nombre":"Kherson International Airport","code":"KHE","region-code":"UA-65","continente":"EU"},
{"id":116,"Nombre":"Roshchino International Airport","code":"TJM","region-code":"RU-TYU","continente":"AS"},
{"id":117,"Nombre":"Tol Airport","code":"TLO","region-code":"PG-EBR","continente":"OC"},
{"id":118,"Nombre":"Gobabis Airport","code":"GOG","region-code":"NA-OH","continente":"AF"},
{"id":119,"Nombre":"Lyon Saint-Exupéry Airport","code":"LYS","region-code":"FR-V","continente":"EU"},
{"id":120,"Nombre":"Clifton Hills Airport","code":"CFH","region-code":"AU-SA","continente":"OC"},
{"id":121,"Nombre":"Upavon Aerodrome","code":"UPV","region-code":"GB-ENG","continente":"EU"},
{"id":122,"Nombre":"Lemoore Naval Air Station (Reeves Field) Airport","code":"NLC","region-code":"US-CA","continente":"NA"},
{"id":123,"Nombre":"Semporna Airport","code":"SMM","region-code":"MY-12","continente":"AS"},
{"id":124,"Nombre":"Dhangarhi Airport","code":"DHI","region-code":"NP-BH","continente":"AS"},
{"id":125,"Nombre":"Roche Harbor Airport","code":"RCE","region-code":"US-WA","continente":"NA"},
{"id":126,"Nombre":"Lugh Ganane Airport","code":"LGX","region-code":"SO-GE","continente":"AF"},
{"id":127,"Nombre":"Capitan FAP Jose A Quinones Gonzales International Airport","code":"CIX","region-code":"PE-LAM","continente":"SA"},
{"id":128,"Nombre":"Prešov Air Base","code":"POV","region-code":"SK-PV","continente":"EU"},
{"id":129,"Nombre":"Akulivik Airport","code":"AKV","region-code":"CA-QC","continente":"NA"},
{"id":130,"Nombre":"St Michael Airport","code":"SMK","region-code":"US-AK","continente":"NA"},
{"id":131,"Nombre":"Djambala Airport","code":"DJM","region-code":"CG-14","continente":"AF"},
{"id":132,"Nombre":"Port Moller Airport","code":"PML","region-code":"US-AK","continente":"NA"},
{"id":133,"Nombre":"Chachoán Airport","code":"ATF","region-code":"EC-T","continente":"SA"},
{"id":134,"Nombre":"Gag Island Airport","code":"GAV","region-code":"ID-PB","continente":"AS"},
{"id":135,"Nombre":"Santa Rosa De Yacuma Airport","code":"SRB","region-code":"BO-B","continente":"SA"},
{"id":136,"Nombre":"Silangit Airport","code":"DTB","region-code":"ID-SU","continente":"AS"},
{"id":137,"Nombre":"Maimun Saleh Airport","code":"SBG","region-code":"ID-AC","continente":"AS"},
{"id":138,"Nombre":"Nondalton Airport","code":"NNL","region-code":"US-AK","continente":"NA"},
{"id":139,"Nombre":"Beijing Daxing International Airport","code":"PKX","region-code":"CN-13","continente":"AS"},
{"id":140,"Nombre":"Fort Nelson Airport","code":"YYE","region-code":"CA-BC","continente":"NA"},
{"id":141,"Nombre":"Triangle North Executive Airport","code":"LFN","region-code":"US-NC","continente":"NA"},
{"id":142,"Nombre":"Dalton Municipal Airport","code":"DNN","region-code":"US-GA","continente":"NA"},
{"id":143,"Nombre":"Skiathos Island National Airport","code":"JSI","region-code":"GR-43","continente":"EU"},
{"id":144,"Nombre":"East Texas Regional Airport","code":"GGG","region-code":"US-TX","continente":"NA"},
{"id":145,"Nombre":"Concepción Airport","code":"CEP","region-code":"BO-S","continente":"SA"},
{"id":146,"Nombre":"Sado Airport","code":"SDS","region-code":"JP-15","continente":"AS"},
{"id":147,"Nombre":"Foya Airport","code":"FOY","region-code":"LR-LO","continente":"AF"},
{"id":148,"Nombre":"Tekadu Airport","code":"TKB","region-code":"PG-MPL","continente":"OC"},
{"id":149,"Nombre":"Akureyri Airport","code":"AEY","region-code":"IS-6","continente":"EU"},
{"id":150,"Nombre":"San Luis Airport","code":"IPI","region-code":"CO-NAR","continente":"SA"},
{"id":151,"Nombre":"Pala Airport","code":"PLF","region-code":"TD-MK","continente":"AF"},
{"id":152,"Nombre":"Cuyahoga County Airport","code":"CGF","region-code":"US-OH","continente":"NA"},
{"id":153,"Nombre":"Oslo Gardermoen Airport","code":"OSL","region-code":"NO-02","continente":"EU"},
{"id":154,"Nombre":"Wycombe Air Park","code":"HYC","region-code":"GB-ENG","continente":"EU"},
{"id":155,"Nombre":"Brawley Municipal Airport","code":"BWC","region-code":"US-CA","continente":"NA"},
{"id":156,"Nombre":"Taskul Airport","code":"TSK","region-code":"PG-SAN","continente":"OC"},
{"id":157,"Nombre":"Gaylord Regional Airport","code":"GLR","region-code":"US-MI","continente":"NA"},
{"id":158,"Nombre":"Benguela Airport","code":"BUG","region-code":"AO-BGU","continente":"AF"},
{"id":159,"Nombre":"Ignacio Agramonte International Airport","code":"CMW","region-code":"CU-09","continente":"NA"},
{"id":160,"Nombre":"José Leonardo Chirinos Airport","code":"CZE","region-code":"VE-I","continente":"SA"},
{"id":161,"Nombre":"Pulau Panjang Airport","code":"PPJ","region-code":"ID-JB","continente":"AS"},
{"id":162,"Nombre":"East 34th Street Heliport","code":"TSS","region-code":"US-NY","continente":"NA"},
{"id":163,"Nombre":"Tabuk Airport","code":"TUU","region-code":"SA-07","continente":"AS"},
{"id":164,"Nombre":"Puerto Jimenez Airport","code":"PJM","region-code":"CR-P","continente":"NA"},
{"id":165,"Nombre":"St-François Airport","code":"SFC","region-code":"GP-U-A","continente":"NA"},
{"id":166,"Nombre":"Meadows Field","code":"BFL","region-code":"US-CA","continente":"NA"},
{"id":167,"Nombre":"Madang Airport","code":"MAG","region-code":"PG-MPM","continente":"OC"},
{"id":168,"Nombre":"Skellefteå Airport","code":"SFT","region-code":"SE-AC","continente":"EU"},
{"id":169,"Nombre":"Ouagadougou Airport","code":"OUA","region-code":"BF-KAD","continente":"AF"},
{"id":170,"Nombre":"Naypyidaw Airport","code":"NYT","region-code":"MM-04","continente":"AS"},
{"id":171,"Nombre":"Tampa North Aero Park Airport","code":"KYO","region-code":"US-FL","continente":"NA"},
{"id":172,"Nombre":"Kiffa Airport","code":"KFA","region-code":"MR-03","continente":"AF"},
{"id":173,"Nombre":"Jasper County Airport","code":"RNZ","region-code":"US-IN","continente":"NA"},
{"id":174,"Nombre":"Hami Airport","code":"HMI","region-code":"CN-65","continente":"AS"},
{"id":175,"Nombre":"Quion Hill Airport","code":"UIQ","region-code":"VU-SEE","continente":"OC"},
{"id":176,"Nombre":"Jiayuguan Airport","code":"JGN","region-code":"CN-62","continente":"AS"},
{"id":177,"Nombre":"Grantsburg Municipal Airport","code":"GTG","region-code":"US-WI","continente":"NA"},
{"id":178,"Nombre":"Valencia Airport","code":"VLC","region-code":"ES-V","continente":"EU"},
{"id":179,"Nombre":"Whiting Field Naval Air Station - North","code":"NSE","region-code":"US-FL","continente":"NA"},
{"id":180,"Nombre":"Naukati Bay Seaplane Base","code":"NKI","region-code":"US-AK","continente":"NA"},
{"id":181,"Nombre":"Losuia Airport","code":"LSA","region-code":"PG-MBA","continente":"OC"},
{"id":182,"Nombre":"Xinyuan Nalati Airport","code":"NLT","region-code":"CN-65","continente":"AS"},
{"id":183,"Nombre":"Marla Airport","code":"MRP","region-code":"AU-SA","continente":"OC"},
{"id":184,"Nombre":"Gregorio Luperon International Airport","code":"POP","region-code":"DO-18","continente":"NA"},
{"id":185,"Nombre":"Rangiroa Airport","code":"RGI","region-code":"PF-U-A","continente":"OC"},
{"id":186,"Nombre":"Aomori Airport","code":"AOJ","region-code":"JP-02","continente":"AS"},
{"id":187,"Nombre":"Culberson County Airport","code":"VHN","region-code":"US-TX","continente":"NA"},
{"id":188,"Nombre":"Enterprise Municipal Airport","code":"ETS","region-code":"US-AL","continente":"NA"},
{"id":189,"Nombre":"Leo Airport","code":"XLU","region-code":"BF-SIS","continente":"AF"},
{"id":190,"Nombre":"Cascade Airport","code":"ICS","region-code":"US-ID","continente":"NA"},
{"id":191,"Nombre":"Wasum Airport","code":"WUM","region-code":"PG-WBK","continente":"OC"},
{"id":192,"Nombre":"Montgomery-Gibbs Executive Airport","code":"MYF","region-code":"US-CA","continente":"NA"},
{"id":193,"Nombre":"Celaque Airport","code":"GAC","region-code":"HN-LE","continente":"NA"},
{"id":194,"Nombre":"Cumaná (Antonio José de Sucre) Airport","code":"CUM","region-code":"VE-R","continente":"SA"},
{"id":195,"Nombre":"Lowcountry Regional Airport","code":"RBW","region-code":"US-SC","continente":"NA"},
{"id":196,"Nombre":"Futaleufú Airport","code":"FFU","region-code":"CL-LL","continente":"SA"},
{"id":197,"Nombre":"Cooinda Airport","code":"CDA","region-code":"AU-NT","continente":"OC"},
{"id":198,"Nombre":"Sahabat [Sahabat 16] Airport","code":"SXS","region-code":"MY-12","continente":"AS"},
{"id":199,"Nombre":"Kerrville Municipal Louis Schreiner Field","code":"ERV","region-code":"US-TX","continente":"NA"},
{"id":200,"Nombre":"Indigo Bay Lodge Airport","code":"IBL","region-code":"MZ-I","continente":"AF"},
{"id":201,"Nombre":"Sua Pan Airport","code":"SXN","region-code":"BW-CE","continente":"AF"},
{"id":202,"Nombre":"Tekirdağ Çorlu Airport","code":"TEQ","region-code":"TR-59","continente":"EU"},
{"id":203,"Nombre":"Paratebueno Airport","code":"EUO","region-code":"CO-CAS","continente":"SA"},
{"id":204,"Nombre":"Vandalia Municipal Airport","code":"VLA","region-code":"US-IL","continente":"NA"},
{"id":205,"Nombre":"Leeds Bradford Airport","code":"LBA","region-code":"GB-ENG","continente":"EU"},
{"id":206,"Nombre":"Suia-Missu Airport","code":"SWM","region-code":"BR-MT","continente":"SA"},
{"id":207,"Nombre":"Tshikapa Airport","code":"TSH","region-code":"CD-KW","continente":"AF"},
{"id":208,"Nombre":"Walvis Bay Airport","code":"WVB","region-code":"NA-ER","continente":"AF"},
{"id":209,"Nombre":"Sibu Airport","code":"SBW","region-code":"MY-13","continente":"AS"},
{"id":210,"Nombre":"Chester County G O Carlson Airport","code":"CTH","region-code":"US-PA","continente":"NA"},
{"id":211,"Nombre":"Gbadolite Airport","code":"BDT","region-code":"CD-EQ","continente":"AF"},
{"id":212,"Nombre":"Armando Schwarck Airport","code":"LPJ","region-code":"VE-F","continente":"SA"},
{"id":213,"Nombre":"Okayama Airport","code":"OKJ","region-code":"JP-33","continente":"AS"},
{"id":214,"Nombre":"St Mary's Airport","code":"KSM","region-code":"US-AK","continente":"NA"},
{"id":215,"Nombre":"Roberts Army Heliport","code":"SYL","region-code":"US-CA","continente":"NA"},
{"id":216,"Nombre":"Port Said Airport","code":"PSD","region-code":"EG-SHR","continente":"AF"},
{"id":217,"Nombre":"Parakou Airport","code":"PKO","region-code":"BJ-BO","continente":"AF"},
{"id":218,"Nombre":"Moundou Airport","code":"MQQ","region-code":"TD-LO","continente":"AF"},
{"id":219,"Nombre":"Sir Seretse Khama International Airport","code":"GBE","region-code":"BW-SE","continente":"AF"},
{"id":220,"Nombre":"Evanston-Uinta County Airport-Burns Field","code":"EVW","region-code":"US-WY","continente":"NA"},
{"id":221,"Nombre":"Asahikawa Airport","code":"AKJ","region-code":"JP-01","continente":"AS"},
{"id":222,"Nombre":"Viracopos International Airport","code":"VCP","region-code":"BR-SP","continente":"SA"},
{"id":223,"Nombre":"Amsterdam Airport Schiphol","code":"AMS","region-code":"NL-NH","continente":"EU"},
{"id":224,"Nombre":"Aalborg Airport","code":"AAL","region-code":"DK-81","continente":"EU"},
{"id":225,"Nombre":"Mélio Viana Airport","code":"QID","region-code":"BR-MG","continente":"SA"},
{"id":226,"Nombre":"Danbury Municipal Airport","code":"DXR","region-code":"US-CT","continente":"NA"},
{"id":227,"Nombre":"Houma Terrebonne Airport","code":"HUM","region-code":"US-LA","continente":"NA"},
{"id":228,"Nombre":"Hyakuri Airport","code":"IBR","region-code":"JP-08","continente":"AS"},
{"id":229,"Nombre":"Chillagoe Airport","code":"LLG","region-code":"AU-QLD","continente":"OC"},
{"id":230,"Nombre":"Fort Liard Airport","code":"YJF","region-code":"CA-NT","continente":"NA"},
{"id":231,"Nombre":"Al Ghaidah International Airport","code":"AAY","region-code":"YE-MR","continente":"AS"},
{"id":232,"Nombre":"Presidente Castro Pinto International Airport","code":"JPA","region-code":"BR-PB","continente":"SA"},
{"id":233,"Nombre":"Juneau International Airport","code":"JNU","region-code":"US-AK","continente":"NA"},
{"id":234,"Nombre":"Lutselk'e Airport","code":"YSG","region-code":"CA-NT","continente":"NA"},
{"id":235,"Nombre":"Poptún Airport","code":"PON","region-code":"GT-PE","continente":"NA"},
{"id":236,"Nombre":"Postville Airport","code":"YSO","region-code":"CA-NL","continente":"NA"},
{"id":237,"Nombre":"Pine Bluff Regional Airport, Grider Field","code":"PBF","region-code":"US-AR","continente":"NA"},
{"id":238,"Nombre":"Asheville Regional Airport","code":"AVL","region-code":"US-NC","continente":"NA"},
{"id":239,"Nombre":"Grants Pass Airport","code":"GTP","region-code":"US-OR","continente":"NA"},
{"id":240,"Nombre":"Jefferson City Memorial Airport","code":"JEF","region-code":"US-MO","continente":"NA"},
{"id":241,"Nombre":"Novo Horizonte Airport","code":"0","region-code":"BR-SP","continente":"SA"},
{"id":242,"Nombre":"Modibo Keita International Airport","code":"BKO","region-code":"ML-2","continente":"AF"},
{"id":243,"Nombre":"Daly River Airport","code":"DVR","region-code":"AU-NT","continente":"OC"},
{"id":244,"Nombre":"Røros Airport","code":"RRS","region-code":"NO-16","continente":"EU"},
{"id":245,"Nombre":"McCall Municipal Airport","code":"MYL","region-code":"US-ID","continente":"NA"},
{"id":246,"Nombre":"Maroantsetra Airport","code":"WMN","region-code":"MG-A","continente":"AF"},
{"id":247,"Nombre":"Ipiranga Airport","code":"IPG","region-code":"BR-AM","continente":"SA"},
{"id":248,"Nombre":"Mekambo Airport","code":"MKB","region-code":"GA-6","continente":"AF"},
{"id":249,"Nombre":"Icy Bay Airport","code":"ICY","region-code":"US-AK","continente":"NA"},
{"id":250,"Nombre":"Teniente FAP Jaime A De Montreuil Morales Airport","code":"CHM","region-code":"PE-ANC","continente":"SA"},
{"id":251,"Nombre":"Njombe Airport","code":"JOM","region-code":"TZ-04","continente":"AF"},
{"id":252,"Nombre":"Wings Field","code":"BBX","region-code":"US-PA","continente":"NA"},
{"id":253,"Nombre":"Longreach Airport","code":"LRE","region-code":"AU-QLD","continente":"OC"},
{"id":254,"Nombre":"N'Djamena International Airport","code":"NDJ","region-code":"TD-CB","continente":"AF"},
{"id":255,"Nombre":"Hamad International Airport","code":"DOH","region-code":"QA-DA","continente":"AS"},
{"id":256,"Nombre":"Ingham Airport","code":"IGH","region-code":"AU-QLD","continente":"OC"},
{"id":257,"Nombre":"Ercan International Airport","code":"ECN","region-code":"CY-02","continente":"AS"},
{"id":258,"Nombre":"Koro Island Airport","code":"KXF","region-code":"FJ-E","continente":"OC"},
{"id":259,"Nombre":"Golovin Airport","code":"GLV","region-code":"US-AK","continente":"NA"},
{"id":260,"Nombre":"Kaintiba Airport","code":"KZF","region-code":"PG-GPK","continente":"OC"},
{"id":261,"Nombre":"Lalmonirhat Airport","code":"LLJ","region-code":"BD-5","continente":"AS"},
{"id":262,"Nombre":"St. Theresa Point Airport","code":"YST","region-code":"CA-MB","continente":"NA"},
{"id":263,"Nombre":"North Platte Regional Airport Lee Bird Field","code":"LBF","region-code":"US-NE","continente":"NA"},
{"id":264,"Nombre":"Olavarria Airport","code":"OVR","region-code":"AR-B","continente":"SA"},
{"id":265,"Nombre":"Nantong Airport","code":"NTG","region-code":"CN-32","continente":"AS"},
{"id":266,"Nombre":"Arthur N Neu Airport","code":"CIN","region-code":"US-IA","continente":"NA"},
{"id":267,"Nombre":"Pevek Airport","code":"PWE","region-code":"RU-CHU","continente":"AS"},
{"id":268,"Nombre":"Bundi Airport","code":"BNT","region-code":"PG-MPM","continente":"OC"},
{"id":269,"Nombre":"Gayndah Airport","code":"GAH","region-code":"AU-QLD","continente":"OC"},
{"id":270,"Nombre":"Santa Fe Municipal Airport","code":"SAF","region-code":"US-NM","continente":"NA"},
{"id":271,"Nombre":"General Francisco Javier Mina International Airport","code":"TAM","region-code":"MX-TAM","continente":"NA"},
{"id":272,"Nombre":"Rochefort-Saint-Agnant (BA 721) Airport","code":"RCO","region-code":"FR-T","continente":"EU"},
{"id":273,"Nombre":"Yevlakh Airport","code":"YLV","region-code":"AZ-YE","continente":"AS"},
{"id":274,"Nombre":"Sahand Airport","code":"ACP","region-code":"IR-01","continente":"AS"},
{"id":275,"Nombre":"San Juan Airport","code":"SJM","region-code":"DO-22","continente":"NA"},
{"id":276,"Nombre":"Rechlin-Lärz Airport","code":"REB","region-code":"DE-MV","continente":"EU"},
{"id":277,"Nombre":"Mweka Airport","code":"MEW","region-code":"CD-KW","continente":"AF"},
{"id":278,"Nombre":"Galway Airport","code":"GWY","region-code":"IE-G","continente":"EU"},
{"id":279,"Nombre":"Kukudu Airport","code":"KUE","region-code":"SB-WE","continente":"OC"},
{"id":280,"Nombre":"Dare County Regional Airport","code":"MEO","region-code":"US-NC","continente":"NA"},
{"id":281,"Nombre":"Corazón de Jesús Airport","code":"CZJ","region-code":"PA-KY","continente":"NA"},
{"id":282,"Nombre":"Opapimiskan Lake Airport","code":"YBS","region-code":"CA-ON","continente":"NA"},
{"id":283,"Nombre":"EMBRAER - Unidade Gavião Peixoto Airport","code":"0","region-code":"BR-SP","continente":"SA"},
{"id":284,"Nombre":"Capitan V A Almonacid Airport","code":"IRJ","region-code":"AR-F","continente":"SA"},
{"id":285,"Nombre":"Paraburdoo Airport","code":"PBO","region-code":"AU-WA","continente":"OC"},
{"id":286,"Nombre":"Sendai Airport","code":"SDJ","region-code":"JP-04","continente":"AS"},
{"id":287,"Nombre":"Niamtougou International Airport","code":"LRL","region-code":"TG-K","continente":"AF"},
{"id":288,"Nombre":"Kamembe Airport","code":"KME","region-code":"RW-04","continente":"AF"},
{"id":289,"Nombre":"Dongshan Airport","code":"HLD","region-code":"CN-15","continente":"AS"},
{"id":290,"Nombre":"Iboki Airport","code":"IBI","region-code":"PG-WBK","continente":"OC"},
{"id":291,"Nombre":"Indigo Bay Lodge Airport","code":"IBL","region-code":"MZ-I","continente":"AF"},
{"id":292,"Nombre":"Chubu Centrair International Airport","code":"NGO","region-code":"JP-23","continente":"AS"},
{"id":293,"Nombre":"Wantoat Airport","code":"WTT","region-code":"PG-MPL","continente":"OC"},
{"id":294,"Nombre":"Bourges Airport","code":"BOU","region-code":"FR-F","continente":"EU"},
{"id":295,"Nombre":"Vanrook Station Airport","code":"VNR","region-code":"AU-QLD","continente":"OC"},
{"id":296,"Nombre":"Renner Field-Goodland Municipal Airport","code":"GLD","region-code":"US-KS","continente":"NA"},
{"id":297,"Nombre":"Tucuma Airport","code":"BR-","region-code":"BR-AM","continente":"SA"},
{"id":298,"Nombre":"Cumaná (Antonio José de Sucre) Airport","code":"CUM","region-code":"VE-R","continente":"SA"},
{"id":299,"Nombre":"Terapo Airport","code":"TEO","region-code":"PG-GPK","continente":"OC"},
{"id":300,"Nombre":"Sanikiluaq Airport","code":"YSK","region-code":"CA-NU","continente":"NA"},
{"id":301,"Nombre":"Shay Gap Airport","code":"SGP","region-code":"AU-WA","continente":"OC"},
{"id":302,"Nombre":"Erie International Tom Ridge Field","code":"ERI","region-code":"US-PA","continente":"NA"},
{"id":303,"Nombre":"Okushiri Airport","code":"OIR","region-code":"JP-01","continente":"AS"},
{"id":304,"Nombre":"Münster Osnabrück Airport","code":"FMO","region-code":"DE-NW","continente":"EU"},
{"id":305,"Nombre":"Shageluk Airport","code":"SHX","region-code":"US-AK","continente":"NA"},
{"id":306,"Nombre":"İncirlik Air Base","code":"UAB","region-code":"TR-01","continente":"AS"},
{"id":307,"Nombre":"Cuamba Airport","code":"FXO","region-code":"MZ-A","continente":"AF"},
{"id":308,"Nombre":"Capitán FAP Guillermo Concha Iberico International Airport","code":"PIU","region-code":"PE-PIU","continente":"SA"},
{"id":309,"Nombre":"Gamal Abdel Nasser Airport","code":"TOB","region-code":"LY-BU","continente":"AF"},
{"id":310,"Nombre":"Chiloquin State Airport","code":"CHZ","region-code":"US-OR","continente":"NA"},
{"id":311,"Nombre":"Parsabade Moghan Airport","code":"PFQ","region-code":"IR-03","continente":"AS"},
{"id":312,"Nombre":"Abu Dhabi International Airport","code":"AUH","region-code":"AE-AZ","continente":"AS"},
{"id":313,"Nombre":"Malé International Airport","code":"MLE","region-code":"MV-MLE","continente":"AS"},
{"id":314,"Nombre":"Eastern WV Regional Airport/Shepherd Field","code":"MRB","region-code":"US-WV","continente":"NA"},
{"id":315,"Nombre":"Cascade Airport","code":"ICS","region-code":"US-ID","continente":"NA"},
{"id":316,"Nombre":"Bertoua Airport","code":"BTA","region-code":"CM-ES","continente":"AF"},
{"id":317,"Nombre":"Los Cabos International Airport","code":"SJD","region-code":"MX-BCS","continente":"NA"},
{"id":318,"Nombre":"Vanrook Station Airport","code":"VNR","region-code":"AU-QLD","continente":"OC"},
{"id":319,"Nombre":"Lokpriya Gopinath Bordoloi International Airport","code":"GAU","region-code":"IN-AS","continente":"AS"},
{"id":320,"Nombre":"Gewayentana Airport","code":"LKA","region-code":"ID-NT","continente":"AS"},
{"id":321,"Nombre":"Rocky Mount Wilson Regional Airport","code":"RWI","region-code":"US-NC","continente":"NA"},
{"id":322,"Nombre":"Aupaluk Airport","code":"YPJ","region-code":"CA-QC","continente":"NA"},
{"id":323,"Nombre":"Bou Saada Airport","code":"BUJ","region-code":"DZ-28","continente":"AF"},
{"id":324,"Nombre":"Mohamed Boudiaf International Airport","code":"CZL","region-code":"DZ-25","continente":"AF"},
{"id":325,"Nombre":"Lennart Meri Tallinn Airport","code":"TLL","region-code":"EE-37","continente":"EU"},
{"id":326,"Nombre":"Washington Island Airstrip","code":"TNQ","region-code":"KI-L","continente":"OC"},
{"id":327,"Nombre":"Chania International Airport","code":"CHQ","region-code":"GR-94","continente":"EU"},
{"id":328,"Nombre":"Smith Point Airport","code":"SHU","region-code":"AU-NT","continente":"OC"},
{"id":329,"Nombre":"Downtown Airpark","code":"DWN","region-code":"US-OK","continente":"NA"},
{"id":330,"Nombre":"Warrnambool Airport","code":"WMB","region-code":"AU-VIC","continente":"OC"},
{"id":331,"Nombre":"East Texas Regional Airport","code":"GGG","region-code":"US-TX","continente":"NA"},
{"id":332,"Nombre":"Dhangarhi Airport","code":"DHI","region-code":"NP-BH","continente":"AS"},
{"id":333,"Nombre":"L.F. Wade International International Airport","code":"BDA","region-code":"BM-U-A","continente":"NA"},
{"id":334,"Nombre":"Isla de Tigre  Heliport","code":"ELX","region-code":"VE-Y","continente":"SA"},
{"id":335,"Nombre":"Caledonia County Airport","code":"LLX","region-code":"US-VT","continente":"NA"},
{"id":336,"Nombre":"Kohat Airport","code":"OHT","region-code":"PK-NW","continente":"AS"},
{"id":337,"Nombre":"Lake Placid Airport","code":"LKP","region-code":"US-NY","continente":"NA"},
{"id":338,"Nombre":"South Jersey Regional Airport","code":"LLY","region-code":"US-NJ","continente":"NA"},
{"id":339,"Nombre":"Buffalo Range Airport","code":"BFO","region-code":"ZW-MV","continente":"AF"},
{"id":340,"Nombre":"Suceava Stefan cel Mare Airport","code":"SCV","region-code":"RO-SV","continente":"EU"},
{"id":341,"Nombre":"Lt Warren Eaton Airport","code":"OIC","region-code":"US-NY","continente":"NA"},
{"id":342,"Nombre":"Minhas Air Base","code":"ATG","region-code":"PK-PB","continente":"AS"},
{"id":343,"Nombre":"Soldotna Airport","code":"SXQ","region-code":"US-AK","continente":"NA"},
{"id":344,"Nombre":"Mount Etjo Airport","code":"MJO","region-code":"NA-OD","continente":"AF"},
{"id":345,"Nombre":"Lake Murray Airport","code":"LMY","region-code":"PG-WPD","continente":"OC"},
{"id":346,"Nombre":"Wevelgem Airport","code":"KJK","region-code":"BE-VWV","continente":"EU"},
{"id":347,"Nombre":"Gooding Municipal Airport","code":"GNG","region-code":"US-ID","continente":"NA"},
{"id":348,"Nombre":"Derim Airport","code":"DER","region-code":"PG-MPL","continente":"OC"},
{"id":349,"Nombre":"Jabalpur Airport","code":"JLR","region-code":"IN-MP","continente":"AS"},
{"id":350,"Nombre":"Barreiras Airport","code":"BRA","region-code":"BR-BA","continente":"SA"},
{"id":351,"Nombre":"Fuzhou Changle International Airport","code":"FOC","region-code":"CN-35","continente":"AS"},
{"id":352,"Nombre":"Baudette International Airport","code":"BDE","region-code":"US-MN","continente":"NA"},
{"id":353,"Nombre":"Fillmore Municipal Airport","code":"FIL","region-code":"US-UT","continente":"NA"},
{"id":354,"Nombre":"Carutapera Airport","code":"CTP","region-code":"BR-MA","continente":"SA"},
{"id":355,"Nombre":"Shaktoolik Airport","code":"SKK","region-code":"US-AK","continente":"NA"},
{"id":356,"Nombre":"Holt Airport","code":"FLI","region-code":"IS-4","continente":"EU"},
{"id":357,"Nombre":"Tamana Island Airport","code":"TMN","region-code":"KI-G","continente":"OC"},
{"id":358,"Nombre":"Tumolbil Airport","code":"TLP","region-code":"PG-SAN","continente":"OC"},
{"id":359,"Nombre":"Sheremetyevo International Airport","code":"SVO","region-code":"RU-MOS","continente":"EU"},
{"id":360,"Nombre":"La Florida Airport","code":"LSC","region-code":"CL-CO","continente":"SA"},
{"id":361,"Nombre":"Njombe Airport","code":"JOM","region-code":"TZ-04","continente":"AF"},
{"id":362,"Nombre":"Kokonau Airport","code":"KOX","region-code":"ID-PA","continente":"AS"},
{"id":363,"Nombre":"Mount Full Stop Airport","code":"MFL","region-code":"AU-QLD","continente":"OC"},
{"id":364,"Nombre":"Concord Municipal Airport","code":"CON","region-code":"US-NH","continente":"NA"},
{"id":365,"Nombre":"Washington County Airport","code":"WSG","region-code":"US-PA","continente":"NA"},
{"id":366,"Nombre":"Fort McMurray Airport","code":"YMM","region-code":"CA-AB","continente":"NA"},
{"id":367,"Nombre":"Esenboğa International Airport","code":"ESB","region-code":"TR-06","continente":"AS"},
{"id":368,"Nombre":"Sitiawan Airport","code":"SWY","region-code":"MY-08","continente":"AS"},
{"id":369,"Nombre":"Pierre Regional Airport","code":"PIR","region-code":"US-SD","continente":"NA"},
{"id":370,"Nombre":"Loen Airport","code":"LOF","region-code":"MH-NMU","continente":"OC"},
{"id":371,"Nombre":"Hassan I Airport","code":"EUN","region-code":"EH-U-A","continente":"AF"},
{"id":372,"Nombre":"Ambatolhy Airport","code":"AHY","region-code":"MG-U","continente":"AF"},
{"id":373,"Nombre":"Gag Island Airport","code":"GAV","region-code":"ID-PB","continente":"AS"},
{"id":374,"Nombre":"Luxembourg-Findel International Airport","code":"LUX","region-code":"LU-L","continente":"EU"},
{"id":375,"Nombre":"Uige Airport","code":"UGO","region-code":"AO-UIG","continente":"AF"},
{"id":376,"Nombre":"Corazón de Jesús Airport","code":"CZJ","region-code":"PA-KY","continente":"NA"},
{"id":377,"Nombre":"Zaraza Airport","code":"ZRZ","region-code":"VE-J","continente":"SA"},
{"id":378,"Nombre":"Mosteiros Airport","code":"MTI","region-code":"CV-S","continente":"AF"},
{"id":379,"Nombre":"Vilhelmina Airport","code":"VHM","region-code":"SE-AC","continente":"EU"},
{"id":380,"Nombre":"Earl Henry Airport","code":"BWL","region-code":"US-OK","continente":"NA"},
{"id":381,"Nombre":"Livengood Camp Airport","code":"LIV","region-code":"US-AK","continente":"NA"},
{"id":382,"Nombre":"Inkerman Airport","code":"IKP","region-code":"AU-QLD","continente":"OC"},
{"id":383,"Nombre":"Kochi Airport (高知空港)","code":"KCZ","region-code":"JP-39","continente":"AS"},
{"id":384,"Nombre":"Bacău Airport","code":"BCM","region-code":"RO-BC","continente":"EU"},
{"id":385,"Nombre":"Bowerman Airport","code":"HQM","region-code":"US-WA","continente":"NA"},
{"id":386,"Nombre":"Dourados Airport","code":"DOU","region-code":"BR-MS","continente":"SA"},
{"id":387,"Nombre":"Comandante Gustavo Kraemer Airport","code":"BGX","region-code":"BR-RS","continente":"SA"},
{"id":388,"Nombre":"EuroAirport Basel-Mulhouse-Freiburg Airport","code":"BSL","region-code":"FR-A","continente":"EU"},
{"id":389,"Nombre":"Tennant Creek Airport","code":"TCA","region-code":"AU-NT","continente":"OC"},
{"id":390,"Nombre":"Cuito Cuanavale Airport","code":"CTI","region-code":"AO-CCU","continente":"AF"},
{"id":391,"Nombre":"Atbara Airport","code":"ATB","region-code":"SD-04","continente":"AF"},
{"id":392,"Nombre":"Inverway Airport","code":"IVW","region-code":"AU-NT","continente":"OC"},
{"id":393,"Nombre":"Taichung Airport","code":"TXG","region-code":"TW-TXG","continente":"AS"},
{"id":394,"Nombre":"Juan Casiano Airport","code":"GPI","region-code":"CO-CAU","continente":"SA"},
{"id":395,"Nombre":"Qaanaaq Airport","code":"NAQ","region-code":"GL-U-A","continente":"NA"},
{"id":396,"Nombre":"Gladstone Airport","code":"GLT","region-code":"AU-QLD","continente":"OC"},
{"id":397,"Nombre":"Waikoloa Heliport","code":"WKL","region-code":"US-HI","continente":"NA"},
{"id":398,"Nombre":"Adıyaman Airport","code":"ADF","region-code":"TR-02","continente":"AS"},
{"id":399,"Nombre":"Hooker Creek Airport","code":"HOK","region-code":"AU-NT","continente":"OC"},
{"id":400,"Nombre":"Lokichoggio Airport","code":"LKG","region-code":"KE-700","continente":"AF"},
{"id":401,"Nombre":"Castellón-Costa Azahar Airport","code":"CDT","region-code":"ES-CS","continente":"EU"},
{"id":402,"Nombre":"Crossville Memorial Whitson Field","code":"CSV","region-code":"US-TN","continente":"NA"},
{"id":403,"Nombre":"Christiansted Harbor Seaplane Base","code":"SSB","region-code":"VI-U-A","continente":"NA"},
{"id":404,"Nombre":"Shahrekord Airport","code":"CQD","region-code":"IR-08","continente":"AS"},
{"id":405,"Nombre":"Fazenda Três Barras Airport","code":"0","region-code":"BR-SP","continente":"SA"},
{"id":406,"Nombre":"Newport State Airport","code":"NPT","region-code":"US-RI","continente":"NA"},
{"id":407,"Nombre":"Akunaq Heliport","code":"QCU","region-code":"GL-U-A","continente":"NA"},
{"id":408,"Nombre":"Oktyabrskiy Airport","code":"OKT","region-code":"RU-TA","continente":"EU"},
{"id":409,"Nombre":"Prince Rupert/Seal Cove Seaplane Base","code":"ZSW","region-code":"CA-BC","continente":"NA"},
{"id":410,"Nombre":"Santa Maria da Vitória Airport","code":"0","region-code":"BR-BA","continente":"SA"},
{"id":411,"Nombre":"Chile Chico Airport","code":"CCH","region-code":"CL-AI","continente":"SA"},
{"id":412,"Nombre":"Ramón Villeda Morales International Airport","code":"SAP","region-code":"HN-CR","continente":"NA"},
{"id":413,"Nombre":"Baitadi Airport","code":"BIT","region-code":"NP-MA","continente":"AS"},
{"id":414,"Nombre":"Port Simpson Seaplane Base","code":"YPI","region-code":"CA-BC","continente":"NA"},
{"id":415,"Nombre":"Raglan Airfield","code":"RAG","region-code":"NZ-WKO","continente":"OC"},
{"id":416,"Nombre":"Nha Trang Air Base","code":"NHA","region-code":"VN-34","continente":"AS"},
{"id":417,"Nombre":"Qala-I-Naw Airport","code":"LQN","region-code":"AF-BDG","continente":"AS"},
{"id":418,"Nombre":"Palmerston North Airport","code":"PMR","region-code":"NZ-MWT","continente":"OC"},
{"id":419,"Nombre":"Quad City International Airport","code":"MLI","region-code":"US-IL","continente":"NA"},
{"id":420,"Nombre":"Ft Devens Moore Army Air Field","code":"AYE","region-code":"US-MA","continente":"NA"},
{"id":421,"Nombre":"Banff Airport","code":"YBA","region-code":"CA-AB","continente":"NA"},
{"id":422,"Nombre":"Abu Musa Island Airport","code":"AEU","region-code":"IR-23","continente":"AS"},
{"id":423,"Nombre":"Ndalatandos Airport","code":"NDF","region-code":"AO-CNO","continente":"AF"},
{"id":424,"Nombre":"Shahid Sadooghi Airport","code":"AZD","region-code":"IR-25","continente":"AS"},
{"id":425,"Nombre":"Tunxi International Airport","code":"TXN","region-code":"CN-34","continente":"AS"},
{"id":426,"Nombre":"Tsletsi Airport","code":"QDJ","region-code":"DZ-17","continente":"AF"},
{"id":427,"Nombre":"Matthews Ridge Airport","code":"MWJ","region-code":"GY-BA","continente":"SA"},
{"id":428,"Nombre":"Marina Municipal Airport","code":"OAR","region-code":"US-CA","continente":"NA"},
{"id":429,"Nombre":"Beaver Airport","code":"WBQ","region-code":"US-AK","continente":"NA"},
{"id":430,"Nombre":"Marion County Regional Airport","code":"FLP","region-code":"US-AR","continente":"NA"},
{"id":431,"Nombre":"Chongqing Jiangbei International Airport","code":"CKG","region-code":"CN-50","continente":"AS"},
{"id":432,"Nombre":"Modlin Airport","code":"WMI","region-code":"PL-MZ","continente":"EU"},
{"id":433,"Nombre":"Koyuk Alfred Adams Airport","code":"KKA","region-code":"US-AK","continente":"NA"},
{"id":434,"Nombre":"Rakanda Airport","code":"RAA","region-code":"PG-EBR","continente":"OC"},
{"id":435,"Nombre":"Talolqan Airport","code":"TQN","region-code":"AF-TAK","continente":"AS"},
{"id":436,"Nombre":"Minami-Daito Airport","code":"MMD","region-code":"JP-47","continente":"AS"},
{"id":437,"Nombre":"Dos Lagunas Airport","code":"DON","region-code":"GT-PE","continente":"NA"},
{"id":438,"Nombre":"Macau International Airport","code":"MFM","region-code":"MO-U-A","continente":"AS"},
{"id":439,"Nombre":"Fort Mackay / Horizon Airport","code":"HZP","region-code":"CA-AB","continente":"NA"},
{"id":440,"Nombre":"Hastings Municipal Airport","code":"HSI","region-code":"US-NE","continente":"NA"},
{"id":441,"Nombre":"Bintulu Airport","code":"BTU","region-code":"MY-13","continente":"AS"},
{"id":442,"Nombre":"Fujairah International Airport","code":"FJR","region-code":"AE-FU","continente":"AS"},
{"id":443,"Nombre":"Greater Cumberland Regional Airport","code":"CBE","region-code":"US-MD","continente":"NA"},
{"id":444,"Nombre":"Bazaruto Island Airport","code":"BZB","region-code":"MZ-I","continente":"AF"},
{"id":445,"Nombre":"Ponta Grossa Airport - Comandante Antonio Amilton Beraldo","code":"PGZ","region-code":"BR-PR","continente":"SA"},
{"id":446,"Nombre":"Blissville Airport","code":"YYS","region-code":"CA-NB","continente":"NA"},
{"id":447,"Nombre":"Meadow Lake Airport","code":"YLJ","region-code":"CA-SK","continente":"NA"},
{"id":448,"Nombre":"Southdowns Airport","code":"KIW","region-code":"ZM-08","continente":"AF"},
{"id":449,"Nombre":"Deputatskiy Airport","code":"DPT","region-code":"RU-SA","continente":"EU"},
{"id":450,"Nombre":"Dalhart Municipal Airport","code":"DHT","region-code":"US-TX","continente":"NA"},
{"id":451,"Nombre":"Simón Bolívar International Airport","code":"CCS","region-code":"VE-X","continente":"SA"},
{"id":452,"Nombre":"Fairfield Municipal Airport","code":"FFL","region-code":"US-IA","continente":"NA"},
{"id":453,"Nombre":"Changzhi Airport","code":"CIH","region-code":"CN-14","continente":"AS"},
{"id":454,"Nombre":"Orcas Island Airport","code":"ESD","region-code":"US-WA","continente":"NA"},
{"id":455,"Nombre":"Dimbokro Airport","code":"DIM","region-code":"CI-11","continente":"AF"},
{"id":456,"Nombre":"Huslia Airport","code":"HSL","region-code":"US-AK","continente":"NA"},
{"id":457,"Nombre":"Glenormiston Airport","code":"GLM","region-code":"AU-QLD","continente":"OC"},
{"id":458,"Nombre":"Port Alice Seaplane Base","code":"PTC","region-code":"US-AK","continente":"NA"},
{"id":459,"Nombre":"Kaolack Airport","code":"KLC","region-code":"SN-FK","continente":"AF"},
{"id":460,"Nombre":"Neftekamsk Airport","code":"NEF","region-code":"RU-BA","continente":"EU"},
{"id":461,"Nombre":"Shageluk Airport","code":"SHX","region-code":"US-AK","continente":"NA"},
{"id":462,"Nombre":"Putumayo Airport","code":"PYO","region-code":"EC-U","continente":"SA"},
{"id":463,"Nombre":"Peretola Airport","code":"FLR","region-code":"IT-52","continente":"EU"},
{"id":464,"Nombre":"Huehuetenango Airport","code":"HUG","region-code":"GT-HU","continente":"NA"},
{"id":465,"Nombre":"Prentice Airport","code":"PRW","region-code":"US-WI","continente":"NA"},
{"id":466,"Nombre":"Birmingham International Airport","code":"BHX","region-code":"GB-ENG","continente":"EU"},
{"id":467,"Nombre":"DeKalb Peachtree Airport","code":"PDK","region-code":"US-GA","continente":"NA"},
{"id":468,"Nombre":"Blissville Airport","code":"YYS","region-code":"CA-NB","continente":"NA"},
{"id":469,"Nombre":"Ketchikan International Airport","code":"KTN","region-code":"US-AK","continente":"NA"},
{"id":470,"Nombre":"Frank Miloye Milenkowichi–Marília State Airport","code":"MII","region-code":"BR-SP","continente":"SA"},
{"id":471,"Nombre":"Miquelon Airport","code":"MQC","region-code":"PM-ML","continente":"NA"},
{"id":472,"Nombre":"Salina Cruz Naval Air Station","code":"SCX","region-code":"MX-OAX","continente":"NA"},
{"id":473,"Nombre":"El Paso International Airport","code":"ELP","region-code":"US-TX","continente":"NA"},
{"id":474,"Nombre":"Dawson Creek Airport","code":"YDQ","region-code":"CA-BC","continente":"NA"},
{"id":475,"Nombre":"Gallatin Field","code":"BZN","region-code":"US-MT","continente":"NA"},
{"id":476,"Nombre":"Coconut Island Airport","code":"CNC","region-code":"AU-QLD","continente":"OC"},
{"id":477,"Nombre":"Ivanof Bay Seaplane Base","code":"KIB","region-code":"US-AK","continente":"NA"},
{"id":478,"Nombre":"Frieda River Airport","code":"FAQ","region-code":"PG-ESW","continente":"OC"},
{"id":479,"Nombre":"Scusciuban Airport","code":"CMS","region-code":"SO-BR","continente":"AF"},
{"id":480,"Nombre":"Caia Airport","code":"CMZ","region-code":"MZ-S","continente":"AF"},
{"id":481,"Nombre":"Rughenda Airfield","code":"RUE","region-code":"CD-NK","continente":"AF"},
{"id":482,"Nombre":"Gorakhpur Airport","code":"GOP","region-code":"IN-UP","continente":"AS"},
{"id":483,"Nombre":"Cagayan de Sulu Airport","code":"CDY","region-code":"PH-TAW","continente":"AS"},
{"id":484,"Nombre":"Roscoe Turner Airport","code":"CRX","region-code":"US-MS","continente":"NA"},
{"id":485,"Nombre":"Moree Airport","code":"MRZ","region-code":"AU-NSW","continente":"OC"},
{"id":486,"Nombre":"Hazleton Municipal Airport","code":"HZL","region-code":"US-PA","continente":"NA"},
{"id":487,"Nombre":"Jacareacanga Airport","code":"JCR","region-code":"BR-PA","continente":"SA"},
{"id":488,"Nombre":"Will Rogers World Airport","code":"OKC","region-code":"US-OK","continente":"NA"},
{"id":489,"Nombre":"Jackson Hole Airport","code":"JAC","region-code":"US-WY","continente":"NA"},
{"id":490,"Nombre":"Red Devil Airport","code":"RDV","region-code":"US-AK","continente":"NA"},
{"id":491,"Nombre":"Khwahan Airport","code":"KWH","region-code":"AF-BDS","continente":"AS"},
{"id":492,"Nombre":"German Olano Air Base","code":"PAL","region-code":"CO-CUN","continente":"SA"},
{"id":493,"Nombre":"Car Nicobar Air Force Station","code":"CBD","region-code":"IN-AN","continente":"AS"},
{"id":494,"Nombre":"Bari Karol Wojtyła Airport","code":"BRI","region-code":"IT-75","continente":"EU"},
{"id":495,"Nombre":"Major Brigadeiro Trompowsky Airport","code":"VAG","region-code":"BR-MG","continente":"SA"},
{"id":496,"Nombre":"Amgu Airport","code":"AEM","region-code":"RU-PRI","continente":"EU"},
{"id":497,"Nombre":"Washington Island Airstrip","code":"TNQ","region-code":"KI-L","continente":"OC"},
{"id":498,"Nombre":"İncirlik Air Base","code":"UAB","region-code":"TR-01","continente":"AS"},
{"id":499,"Nombre":"Green River Airport","code":"GVI","region-code":"PG-SAN","continente":"OC"},
{"id":500,"Nombre":"Playa del Carmen Airport","code":"PCM","region-code":"MX-ROO","continente":"NA"},
{"id":501,"Nombre":"Perito Moreno Airport","code":"PMQ","region-code":"AR-Z","continente":"SA"},
{"id":502,"Nombre":"Les Sables-d'Olonne Talmont Airport","code":"LSO","region-code":"FR-R","continente":"EU"},
{"id":503,"Nombre":"Sultan Thaha Airport","code":"DJB","region-code":"ID-JA","continente":"AS"},
{"id":504,"Nombre":"Higuerote Airport","code":"HGE","region-code":"VE-M","continente":"SA"},
{"id":505,"Nombre":"Croydon Airport","code":"CDQ","region-code":"AU-QLD","continente":"OC"},
{"id":506,"Nombre":"El Dorado International Airport","code":"BOG","region-code":"CO-CUN","continente":"SA"},
{"id":507,"Nombre":"Chinguetti Airport","code":"CGT","region-code":"MR-07","continente":"AF"},
{"id":508,"Nombre":"Tongareva Airport","code":"PYE","region-code":"CK-U-A","continente":"OC"},
{"id":509,"Nombre":"Nyagan Airport","code":"NYA","region-code":"RU-KHM","continente":"EU"},
{"id":510,"Nombre":"Gangneung Airport (K-18)","code":"KAG","region-code":"KR-42","continente":"AS"},
{"id":511,"Nombre":"Manapouri Airport","code":"TEU","region-code":"NZ-STL","continente":"OC"},
{"id":512,"Nombre":"Gitega Airport","code":"GID","region-code":"BI-GI","continente":"AF"},
{"id":513,"Nombre":"Pacific City State Airport","code":"PFC","region-code":"US-OR","continente":"NA"},
{"id":514,"Nombre":"Waimea Kohala Airport","code":"MUE","region-code":"US-HI","continente":"NA"},
{"id":515,"Nombre":"Willows Glenn County Airport","code":"WLW","region-code":"US-CA","continente":"NA"},
{"id":516,"Nombre":"Castro Airport","code":"QAC","region-code":"BR-PR","continente":"SA"},
{"id":517,"Nombre":"Cabo 1° Juan Román Airport","code":"WPA","region-code":"CL-AI","continente":"SA"},
{"id":518,"Nombre":"Piarco International Airport","code":"POS","region-code":"TT-TUP","continente":"NA"},
{"id":519,"Nombre":"General Francisco Bermúdez Airport","code":"CUP","region-code":"VE-R","continente":"SA"},
{"id":520,"Nombre":"Arathusa Safari Lodge Airport","code":"ASS","region-code":"ZA-NP","continente":"AF"},
{"id":521,"Nombre":"Harrisburg International Airport","code":"MDT","region-code":"US-PA","continente":"NA"},
{"id":522,"Nombre":"Muir Army Air Field (Fort Indiantown Gap) Airport","code":"MUI","region-code":"US-PA","continente":"NA"},
{"id":523,"Nombre":"Ashland Municipal Sumner Parker Field","code":"AHM","region-code":"US-OR","continente":"NA"},
{"id":524,"Nombre":"Rickenbacker International Airport","code":"LCK","region-code":"US-OH","continente":"NA"},
{"id":525,"Nombre":"Savé Airport","code":"SVF","region-code":"BJ-CO","continente":"AF"},
{"id":526,"Nombre":"Forest City Municipal Airport","code":"FXY","region-code":"US-IA","continente":"NA"},
{"id":527,"Nombre":"Milford Sound Airport","code":"MFN","region-code":"NZ-STL","continente":"OC"},
{"id":528,"Nombre":"Esperance Airport","code":"EPR","region-code":"AU-WA","continente":"OC"},
{"id":529,"Nombre":"Åre Östersund Airport","code":"OSD","region-code":"SE-Z","continente":"EU"},
{"id":530,"Nombre":"Center Island Airport","code":"CWS","region-code":"US-WA","continente":"NA"},
{"id":531,"Nombre":"Lawrenceville Brunswick Municipal Airport","code":"LVL","region-code":"US-VA","continente":"NA"},
{"id":532,"Nombre":"Lady Franklin Point Airport","code":"YUJ","region-code":"CA-NU","continente":"NA"},
{"id":533,"Nombre":"Thorshofn Airport","code":"THO","region-code":"IS-6","continente":"EU"},
{"id":534,"Nombre":"Childress Municipal Airport","code":"CDS","region-code":"US-TX","continente":"NA"},
{"id":535,"Nombre":"Douglas Municipal Airport","code":"DGL","region-code":"US-AZ","continente":"NA"},
{"id":536,"Nombre":"Pattaya Airpark","code":"PYX","region-code":"TH-20","continente":"AS"},
{"id":537,"Nombre":"Orocue Airport","code":"ORC","region-code":"CO-CAS","continente":"SA"},
{"id":538,"Nombre":"Luis Munoz Marin International Airport","code":"SJU","region-code":"PR-U-A","continente":"NA"},
{"id":539,"Nombre":"Manjimup Airport","code":"MJP","region-code":"AU-WA","continente":"OC"},
{"id":540,"Nombre":"Owen Roberts International Airport","code":"GCM","region-code":"KY-U-A","continente":"NA"},
{"id":541,"Nombre":"Baton Rouge Metropolitan Airport","code":"BTR","region-code":"US-LA","continente":"NA"},
{"id":542,"Nombre":"Saint-Yan Airport","code":"SYT","region-code":"FR-D","continente":"EU"},
{"id":543,"Nombre":"Metema Airport","code":"ETE","region-code":"ET-AM","continente":"AF"},
{"id":544,"Nombre":"Manakara Airport","code":"WVK","region-code":"MG-F","continente":"AF"},
{"id":545,"Nombre":"Tougan Airport","code":"TUQ","region-code":"BF-SOR","continente":"AF"},
{"id":546,"Nombre":"Cholet Le Pontreau Airport","code":"CET","region-code":"FR-R","continente":"EU"},
{"id":547,"Nombre":"San Juan Del César Airport","code":"SJH","region-code":"CO-CES","continente":"SA"},
{"id":548,"Nombre":"Banjul International Airport","code":"BJL","region-code":"GM-W","continente":"AF"},
{"id":549,"Nombre":"OR Tambo International Airport","code":"JNB","region-code":"ZA-GT","continente":"AF"},
{"id":550,"Nombre":"Trombetas Airport","code":"TMT","region-code":"BR-PA","continente":"SA"},
{"id":551,"Nombre":"Brno-Tuřany Airport","code":"BRQ","region-code":"CZ-JM","continente":"EU"},
{"id":552,"Nombre":"Hobart International Airport","code":"HBA","region-code":"AU-TAS","continente":"OC"},
{"id":553,"Nombre":"Sde Dov Airport","code":"SDV","region-code":"IL-TA","continente":"AS"},
{"id":554,"Nombre":"Abilene Regional Airport","code":"ABI","region-code":"US-TX","continente":"NA"},
{"id":555,"Nombre":"Ipil Airport","code":"IPE","region-code":"PH-ZSI","continente":"AS"},
{"id":556,"Nombre":"Katiu Airport","code":"KXU","region-code":"PF-U-A","continente":"OC"},
{"id":557,"Nombre":"Gimpo International Airport","code":"GMP","region-code":"KR-11","continente":"AS"},
{"id":558,"Nombre":"Maximo Gomez Airport","code":"AVI","region-code":"CU-08","continente":"NA"},
{"id":559,"Nombre":"Ekuk Airport","code":"KKU","region-code":"US-AK","continente":"NA"},
{"id":560,"Nombre":"Mecheria Airport","code":"MZW","region-code":"DZ-45","continente":"AF"},
{"id":561,"Nombre":"General Mitchell International Airport","code":"MKE","region-code":"US-WI","continente":"NA"},
{"id":562,"Nombre":"Dundee Airport","code":"DND","region-code":"GB-SCT","continente":"EU"},
{"id":563,"Nombre":"Henri Coandă International Airport","code":"OTP","region-code":"RO-B","continente":"EU"},
{"id":564,"Nombre":"Lipetsk Airport","code":"LPK","region-code":"RU-LIP","continente":"EU"},
{"id":565,"Nombre":"Aviano Air Base","code":"AVB","region-code":"IT-36","continente":"EU"},
{"id":566,"Nombre":"Appleton International Airport","code":"ATW","region-code":"US-WI","continente":"NA"},
{"id":567,"Nombre":"Capt Justiniano Montenegro Airport","code":"PDM","region-code":"PA-7","continente":"NA"},
{"id":568,"Nombre":"Gassim Airport","code":"ELQ","region-code":"SA-05","continente":"AS"},
{"id":569,"Nombre":"Parndana Airport","code":"PDN","region-code":"AU-SA","continente":"OC"},
{"id":570,"Nombre":"Machu Pichu Airport","code":"MFT","region-code":"PE-HUC","continente":"SA"},
{"id":571,"Nombre":"Shaheed Benazirabad Airport","code":"WNS","region-code":"PK-SD","continente":"AS"},
{"id":572,"Nombre":"Stord Airport","code":"SRP","region-code":"NO-12","continente":"EU"},
{"id":573,"Nombre":"Reconquista Airport","code":"RCQ","region-code":"AR-S","continente":"SA"},
{"id":574,"Nombre":"Port Hope Simpson Airport","code":"YHA","region-code":"CA-NL","continente":"NA"},
{"id":575,"Nombre":"Nyagan Airport","code":"NYA","region-code":"RU-KHM","continente":"EU"},
{"id":576,"Nombre":"Range Regional Airport","code":"HIB","region-code":"US-MN","continente":"NA"},
{"id":577,"Nombre":"Amderma Airport","code":"AMV","region-code":"RU-NEN","continente":"AS"},
{"id":578,"Nombre":"Buffalo Spring","code":"UAS","region-code":"KE-700","continente":"AF"},
{"id":579,"Nombre":"Bentota River Waterdrome","code":"BJT","region-code":"LK-1","continente":"AS"},
{"id":580,"Nombre":"Columbia County Airport","code":"HCC","region-code":"US-NY","continente":"NA"},
{"id":581,"Nombre":"Santa Paula Airport","code":"0","region-code":"BR-SP","continente":"SA"},
{"id":582,"Nombre":"Sirri Island Airport","code":"SXI","region-code":"IR-23","continente":"AS"},
{"id":583,"Nombre":"Kepi Airport","code":"KEI","region-code":"ID-PA","continente":"AS"},
{"id":584,"Nombre":"Steamboat Bay Seaplane Base","code":"WSB","region-code":"US-AK","continente":"NA"},
{"id":585,"Nombre":"Stokmarknes Skagen Airport","code":"SKN","region-code":"NO-18","continente":"EU"},
{"id":586,"Nombre":"Dali Airport","code":"DLU","region-code":"CN-53","continente":"AS"},
{"id":587,"Nombre":"Daegu Airport","code":"TAE","region-code":"KR-27","continente":"AS"},
{"id":588,"Nombre":"Mopti Airport","code":"MZI","region-code":"ML-5","continente":"AF"},
{"id":589,"Nombre":"Pongtiku Airport","code":"TTR","region-code":"ID-SN","continente":"AS"},
{"id":590,"Nombre":"Torrington Municipal Airport","code":"TOR","region-code":"US-WY","continente":"NA"},
{"id":591,"Nombre":"Antrim County Airport","code":"ACB","region-code":"US-MI","continente":"NA"},
{"id":592,"Nombre":"Sierra Vista Municipal Libby Army Air Field","code":"FHU","region-code":"US-AZ","continente":"NA"},
{"id":593,"Nombre":"Hrodna Airport","code":"GNA","region-code":"BY-HR","continente":"EU"},
{"id":594,"Nombre":"Treasure Cay Airport","code":"TCB","region-code":"BS-MH","continente":"NA"},
{"id":595,"Nombre":"Ricardo García Posada Airport","code":"ESR","region-code":"CL-AT","continente":"SA"},
{"id":596,"Nombre":"Santana Ramos Airport","code":"SRO","region-code":"CO-HUI","continente":"SA"},
{"id":597,"Nombre":"Useless Loop Airport","code":"USL","region-code":"AU-WA","continente":"OC"},
{"id":598,"Nombre":"Meselia Airport","code":"MFZ","region-code":"PG-WBK","continente":"OC"},
{"id":599,"Nombre":"Lakeba Island Airport","code":"LKB","region-code":"FJ-E","continente":"OC"},
{"id":600,"Nombre":"Nutwood Downs Airport","code":"UTD","region-code":"AU-NT","continente":"OC"},
{"id":601,"Nombre":"Nevatim Air Base","code":"VTM","region-code":"IL-D","continente":"AS"},
{"id":602,"Nombre":"Willow Airport","code":"WOW","region-code":"US-AK","continente":"NA"},
{"id":603,"Nombre":"Jabalpur Airport","code":"JLR","region-code":"IN-MP","continente":"AS"},
{"id":604,"Nombre":"Stung Treng Airport","code":"TNX","region-code":"KH-19","continente":"AS"},
{"id":605,"Nombre":"Motswari Airport","code":"MWR","region-code":"ZA-MP","continente":"AF"},
{"id":606,"Nombre":"Selaparang Airport","code":"AMI","region-code":"ID-NB","continente":"AS"},
{"id":607,"Nombre":"Penza Airport","code":"PEZ","region-code":"RU-PNZ","continente":"EU"},
{"id":608,"Nombre":"Shah Amanat International Airport","code":"CGP","region-code":"BD-2","continente":"AS"},
{"id":609,"Nombre":"Kongolo Airport","code":"KOO","region-code":"CD-KA","continente":"AF"},
{"id":610,"Nombre":"Ascención De Guarayos Airport","code":"ASC","region-code":"BO-S","continente":"SA"},
{"id":611,"Nombre":"Sabu-Tardanu Airport","code":"SAU","region-code":"ID-NT","continente":"AS"},
{"id":612,"Nombre":"Yakushima Airport","code":"KUM","region-code":"JP-46","continente":"AS"},
{"id":613,"Nombre":"Oum Hadjer Airport","code":"OUM","region-code":"TD-BA","continente":"AF"},
{"id":614,"Nombre":"El Minya Airport","code":"EMY","region-code":"EG-MN","continente":"AF"},
{"id":615,"Nombre":"Skövde Airport","code":"KVB","region-code":"SE-Q","continente":"EU"},
{"id":616,"Nombre":"Batesville Regional Airport","code":"BVX","region-code":"US-AR","continente":"NA"},
{"id":617,"Nombre":"Huntingburg Airport","code":"HNB","region-code":"US-IN","continente":"NA"},
{"id":618,"Nombre":"Waco Regional Airport","code":"ACT","region-code":"US-TX","continente":"NA"},
{"id":619,"Nombre":"Miami Seaplane Base","code":"MPB","region-code":"US-FL","continente":"NA"},
{"id":620,"Nombre":"Kungim Airport","code":"KGM","region-code":"PG-WPD","continente":"OC"},
{"id":621,"Nombre":"Penn Valley Airport","code":"SEG","region-code":"US-PA","continente":"NA"},
{"id":622,"Nombre":"Kayes Dag Dag Airport","code":"KYS","region-code":"ML-1","continente":"AF"},
{"id":623,"Nombre":"Ivishak Airport","code":"IVH","region-code":"US-AK","continente":"NA"},
{"id":624,"Nombre":"Bandanaira Airport","code":"NDA","region-code":"ID-MA","continente":"AS"},
{"id":625,"Nombre":"Quzhou Airport","code":"JUZ","region-code":"CN-33","continente":"AS"},
{"id":626,"Nombre":"Captain Ramon Xatruch Airport","code":"PLP","region-code":"PA-5","continente":"NA"},
{"id":627,"Nombre":"Amado Nervo National Airport","code":"TPQ","region-code":"MX-NAY","continente":"NA"},
{"id":628,"Nombre":"Southdowns Airport","code":"KIW","region-code":"ZM-08","continente":"AF"},
{"id":629,"Nombre":"Shepparton Airport","code":"SHT","region-code":"AU-VIC","continente":"OC"},
{"id":630,"Nombre":"Toussaint Louverture International Airport","code":"PAP","region-code":"HT-OU","continente":"NA"},
{"id":631,"Nombre":"Alula Airport","code":"ALU","region-code":"SO-BR","continente":"AF"},
{"id":632,"Nombre":"Cupul Airport","code":"TZM","region-code":"MX-YUC","continente":"NA"},
{"id":633,"Nombre":"Nantucket Memorial Airport","code":"ACK","region-code":"US-MA","continente":"NA"},
{"id":634,"Nombre":"Balakovo Airport","code":"BWO","region-code":"RU-SAR","continente":"EU"},
{"id":635,"Nombre":"Siegerland Airport","code":"SGE","region-code":"DE-NW","continente":"EU"},
{"id":636,"Nombre":"Kandep Airport","code":"KDP","region-code":"PG-EPW","continente":"OC"},
{"id":637,"Nombre":"Brunswick Executive Airport","code":"NHZ","region-code":"US-ME","continente":"NA"},
{"id":638,"Nombre":"Ukunda Airstrip","code":"UKA","region-code":"KE-300","continente":"AF"},
{"id":639,"Nombre":"Tchibanga Airport","code":"TCH","region-code":"GA-5","continente":"AF"},
{"id":640,"Nombre":"Pathein Airport","code":"BSX","region-code":"MM-07","continente":"AS"},
{"id":641,"Nombre":"Ladouanie Airport","code":"LDO","region-code":"SR-SI","continente":"SA"},
{"id":642,"Nombre":"Anaktuvuk Pass Airport","code":"AKP","region-code":"US-AK","continente":"NA"},
{"id":643,"Nombre":"Jackpot Airport/Hayden Field","code":"KPT","region-code":"US-NV","continente":"NA"},
{"id":644,"Nombre":"Fundación Airport","code":"FDA","region-code":"CO-MAG","continente":"SA"},
{"id":645,"Nombre":"Buariki Airport","code":"AAK","region-code":"KI-G","continente":"OC"},
{"id":646,"Nombre":"Magdagachi Airport","code":"GDG","region-code":"RU-AMU","continente":"EU"},
{"id":647,"Nombre":"Pau Pyrénées Airport","code":"PUF","region-code":"FR-B","continente":"EU"},
{"id":648,"Nombre":"Rostock-Laage Airport","code":"RLG","region-code":"DE-MV","continente":"EU"},
{"id":649,"Nombre":"Portage Creek Airport","code":"PCA","region-code":"US-AK","continente":"NA"},
{"id":650,"Nombre":"General Villamil Airport","code":"IBB","region-code":"EC-W","continente":"SA"},
{"id":651,"Nombre":"Berlin Brandenburg Airport (U.C.)","code":"BER","region-code":"DE-BR","continente":"EU"},
{"id":652,"Nombre":"Decatur Airport","code":"DEC","region-code":"US-IL","continente":"NA"},
{"id":653,"Nombre":"Reao Airport","code":"REA","region-code":"PF-U-A","continente":"OC"},
{"id":654,"Nombre":"Kangiqsujuaq (Wakeham Bay) Airport","code":"YWB","region-code":"CA-QC","continente":"NA"},
{"id":655,"Nombre":"Ta'izz International Airport","code":"TAI","region-code":"YE-TA","continente":"AS"},
{"id":656,"Nombre":"Del Norte International Airport","code":"NTR","region-code":"MX-NLE","continente":"NA"},
{"id":657,"Nombre":"Portland International Jetport Airport","code":"PWM","region-code":"US-ME","continente":"NA"},
{"id":658,"Nombre":"Haelogo Airport","code":"HEO","region-code":"PG-CPM","continente":"OC"},
{"id":659,"Nombre":"Emalamo Sanana Airport","code":"SQN","region-code":"ID-MU","continente":"AS"},
{"id":660,"Nombre":"Yam Island Airport","code":"XMY","region-code":"AU-QLD","continente":"OC"},
{"id":661,"Nombre":"Durrie Airport","code":"DRR","region-code":"AU-QLD","continente":"OC"},
{"id":662,"Nombre":"Leaf Rapids Airport","code":"YLR","region-code":"CA-MB","continente":"NA"},
{"id":663,"Nombre":"Naoro Airport","code":"NOO","region-code":"PG-CPM","continente":"OC"},
{"id":664,"Nombre":"Charlotte Amalie Harbor Seaplane Base","code":"SPB","region-code":"VI-U-A","continente":"NA"},
{"id":665,"Nombre":"Albert Whitted Airport","code":"SPG","region-code":"US-FL","continente":"NA"},
{"id":666,"Nombre":"Perry Island Seaplane Base","code":"PYL","region-code":"US-AK","continente":"NA"},
{"id":667,"Nombre":"Antonio Roldan Betancourt Airport","code":"APO","region-code":"CO-ANT","continente":"SA"},
{"id":668,"Nombre":"Pasir Pangaraan Airport","code":"PPR","region-code":"ID-RI","continente":"AS"},
{"id":669,"Nombre":"Middleton Island Airport","code":"MDO","region-code":"US-AK","continente":"NA"},
{"id":670,"Nombre":"Del Rio International Airport","code":"DRT","region-code":"US-TX","continente":"NA"},
{"id":671,"Nombre":"Bambu Airport","code":"BCP","region-code":"PG-MPM","continente":"OC"},
{"id":672,"Nombre":"Key Field","code":"MEI","region-code":"US-MS","continente":"NA"},
{"id":673,"Nombre":"Eelde Airport","code":"GRQ","region-code":"NL-DR","continente":"EU"},
{"id":674,"Nombre":"Ngjiva Pereira Airport","code":"VPE","region-code":"AO-CNN","continente":"AF"},
{"id":675,"Nombre":"Isisford Airport","code":"ISI","region-code":"AU-QLD","continente":"OC"},
{"id":676,"Nombre":"La Chorrera Airport","code":"LCR","region-code":"CO-AMA","continente":"SA"},
{"id":677,"Nombre":"Sky Harbor Airport","code":"OBK","region-code":"US-IL","continente":"NA"},
{"id":678,"Nombre":"Nadi International Airport","code":"NAN","region-code":"FJ-W","continente":"OC"},
{"id":679,"Nombre":"Independence Municipal Airport","code":"IDP","region-code":"US-KS","continente":"NA"},
{"id":680,"Nombre":"Asmara International Airport","code":"ASM","region-code":"ER-SK","continente":"AF"},
{"id":681,"Nombre":"Yagoua Airport","code":"GXX","region-code":"CM-EN","continente":"AF"},
{"id":682,"Nombre":"Grant County International Airport","code":"MWH","region-code":"US-WA","continente":"NA"},
{"id":683,"Nombre":"San Felipe International Airport","code":"SFH","region-code":"MX-BCN","continente":"NA"},
{"id":684,"Nombre":"Dutchess County Airport","code":"POU","region-code":"US-NY","continente":"NA"},
{"id":685,"Nombre":"Xinzhou Wutaishan Airport","code":"WUT","region-code":"CN-14","continente":"AS"},
{"id":686,"Nombre":"Sandspit Airport","code":"YZP","region-code":"CA-BC","continente":"NA"},
{"id":687,"Nombre":"Santa Bernardina International Airport","code":"DZO","region-code":"UY-DU","continente":"SA"},
{"id":688,"Nombre":"Sidney - Richland Regional Airport","code":"SDY","region-code":"US-MT","continente":"NA"},
{"id":689,"Nombre":"Kuantan Airport","code":"KUA","region-code":"MY-06","continente":"AS"},
{"id":690,"Nombre":"Yining Airport","code":"YIN","region-code":"CN-65","continente":"AS"},
{"id":691,"Nombre":"Gothenburg City Airport","code":"GSE","region-code":"SE-Q","continente":"EU"},
{"id":692,"Nombre":"Antsirabato Airport","code":"ANM","region-code":"MG-D","continente":"AF"},
{"id":693,"Nombre":"Pulau Panjang Airport","code":"PPJ","region-code":"ID-JB","continente":"AS"},
{"id":694,"Nombre":"General Manuel Serrano Airport","code":"MCH","region-code":"EC-O","continente":"SA"},
{"id":695,"Nombre":"Campbell River Airport","code":"YBL","region-code":"CA-BC","continente":"NA"},
{"id":696,"Nombre":"Ust-Tsylma Airport","code":"UTS","region-code":"RU-KO","continente":"EU"},
{"id":697,"Nombre":"Palmas del Mar Airstrip","code":"PPD","region-code":"PR-U-A","continente":"NA"},
{"id":698,"Nombre":"Beja Airport / Airbase","code":"BYJ","region-code":"PT-02","continente":"EU"},
{"id":699,"Nombre":"Devonport Airport","code":"DPO","region-code":"AU-TAS","continente":"OC"},
{"id":700,"Nombre":"Kanas Airport","code":"KJI","region-code":"CN-65","continente":"AS"},
{"id":701,"Nombre":"Lubbock Preston Smith International Airport","code":"LBB","region-code":"US-TX","continente":"NA"},
{"id":702,"Nombre":"Brunette Downs Airport","code":"BTD","region-code":"AU-NT","continente":"OC"},
{"id":703,"Nombre":"Puerto Barrios Airport","code":"PBR","region-code":"GT-IZ","continente":"NA"},
{"id":704,"Nombre":"Coronel Horácio de Mattos Airport","code":"LEC","region-code":"BR-BA","continente":"SA"},
{"id":705,"Nombre":"Vorkuta Airport","code":"VKT","region-code":"RU-KO","continente":"AS"},
{"id":706,"Nombre":"Glenwood Springs Municipal Airport","code":"GWS","region-code":"US-CO","continente":"NA"},
{"id":707,"Nombre":"Michigan City Municipal Airport","code":"MGC","region-code":"US-IN","continente":"NA"},
{"id":708,"Nombre":"Nelson Airport","code":"NSN","region-code":"NZ-NSN","continente":"OC"},
{"id":709,"Nombre":"Mbala Airport","code":"MMQ","region-code":"ZM-05","continente":"AF"},
{"id":710,"Nombre":"Colatina Airport","code":"QCH","region-code":"BR-ES","continente":"SA"},
{"id":711,"Nombre":"Red Deer Regional Airport","code":"YQF","region-code":"CA-AB","continente":"NA"},
{"id":712,"Nombre":"Hissar Airport","code":"HSS","region-code":"IN-HR","continente":"AS"},
{"id":713,"Nombre":"Khwai River Lodge Airport","code":"KHW","region-code":"BW-NW","continente":"AF"},
{"id":714,"Nombre":"Thompson-Robbins Airport","code":"HEE","region-code":"US-AR","continente":"NA"},
{"id":715,"Nombre":"Faranah Airport","code":"FAA","region-code":"GN-F","continente":"AF"},
{"id":716,"Nombre":"Savusavu Airport","code":"SVU","region-code":"FJ-N","continente":"OC"},
{"id":717,"Nombre":"Skylark Field","code":"ILE","region-code":"US-TX","continente":"NA"},
{"id":718,"Nombre":"Dubrovnik Airport","code":"DBV","region-code":"HR-19","continente":"EU"},
{"id":719,"Nombre":"Falcon Field","code":"MSC","region-code":"US-AZ","continente":"NA"},
{"id":720,"Nombre":"Hyder Seaplane Base","code":"WHD","region-code":"US-AK","continente":"NA"},
{"id":721,"Nombre":"Point Mugu Naval Air Station (Naval Base Ventura Co)","code":"NTD","region-code":"US-CA","continente":"NA"},
{"id":722,"Nombre":"Point Salines International Airport","code":"GND","region-code":"GD-GE","continente":"NA"},
{"id":723,"Nombre":"Gwaunaru'u Airport","code":"AKS","region-code":"SB-ML","continente":"OC"},
{"id":724,"Nombre":"Mulan Airport","code":"LGE","region-code":"AU-WA","continente":"OC"},
{"id":725,"Nombre":"Sovetskiy Airport","code":"OVS","region-code":"RU-KHM","continente":"AS"},
{"id":726,"Nombre":"Whalsay Airport","code":"WHS","region-code":"GB-SCT","continente":"EU"},
{"id":727,"Nombre":"Middletown Regional Airport","code":"MWO","region-code":"US-OH","continente":"NA"},
{"id":728,"Nombre":"Banaina Airport","code":"NAF","region-code":"ID-KU","continente":"AS"},
{"id":729,"Nombre":"Bremerton National Airport","code":"PWT","region-code":"US-WA","continente":"NA"},
{"id":730,"Nombre":"Greenville Sinoe Airport","code":"SNI","region-code":"LR-SI","continente":"AF"},
{"id":731,"Nombre":"Nyeri Airport","code":"NYE","region-code":"KE-200","continente":"AF"},
{"id":732,"Nombre":"Gora Airstrip","code":"GOC","region-code":"PG-NPP","continente":"OC"},
{"id":733,"Nombre":"Quthing Airport","code":"UTG","region-code":"LS-G","continente":"AF"},
{"id":734,"Nombre":"Siwa Oasis North Airport","code":"SEW","region-code":"EG-MT","continente":"AF"},
{"id":735,"Nombre":"Sir Grantley Adams International Airport","code":"BGI","region-code":"BB-01","continente":"NA"},
{"id":736,"Nombre":"Mindiptana Airport","code":"MDP","region-code":"ID-PA","continente":"AS"},
{"id":737,"Nombre":"Kiev Zhuliany International Airport","code":"IEV","region-code":"UA-32","continente":"EU"},
{"id":738,"Nombre":"Lijiang Airport","code":"LJG","region-code":"CN-53","continente":"AS"},
{"id":739,"Nombre":"Waycross Ware County Airport","code":"AYS","region-code":"US-GA","continente":"NA"},
{"id":740,"Nombre":"Moshi Airport","code":"QSI","region-code":"TZ-09","continente":"AF"},
{"id":741,"Nombre":"Deputado Luiz Eduardo Magalhães International Airport","code":"SSA","region-code":"BR-BA","continente":"SA"},
{"id":742,"Nombre":"Pryor Field Regional Airport","code":"DCU","region-code":"US-AL","continente":"NA"},
{"id":743,"Nombre":"Faro Airport","code":"FAO","region-code":"PT-08","continente":"EU"},
{"id":744,"Nombre":"Lukulu Airport","code":"LXU","region-code":"ZM-01","continente":"AF"},
{"id":745,"Nombre":"Migalovo Air Base","code":"KLD","region-code":"RU-TVE","continente":"EU"},
{"id":746,"Nombre":"Ouesso Airport","code":"OUE","region-code":"CG-13","continente":"AF"},
{"id":747,"Nombre":"Bazhong Enyang Airport","code":"BZX","region-code":"CN-51","continente":"AS"},
{"id":748,"Nombre":"LTS Pulau Redang Airport","code":"RDN","region-code":"MY-11","continente":"AS"},
{"id":749,"Nombre":"Namsos Høknesøra Airport","code":"OSY","region-code":"NO-17","continente":"EU"},
{"id":750,"Nombre":"Brunette Downs Airport","code":"BTD","region-code":"AU-NT","continente":"OC"},
{"id":751,"Nombre":"Mili Island Airport","code":"MIJ","region-code":"MH-MIL","continente":"OC"},
{"id":752,"Nombre":"Oslo, Fornebu Airport","code":"FBU","region-code":"NO-03","continente":"EU"},
{"id":753,"Nombre":"Béziers-Vias Airport","code":"BZR","region-code":"FR-K","continente":"EU"},
{"id":754,"Nombre":"Kirkuk Air Base","code":"KIK","region-code":"IQ-TS","continente":"AS"},
{"id":755,"Nombre":"Novo Aripuanã Airport","code":"NVP","region-code":"BR-AM","continente":"SA"},
{"id":756,"Nombre":"Mehrabad International Airport","code":"THR","region-code":"IR-07","continente":"AS"},
{"id":757,"Nombre":"Wilkes County Airport","code":"IKB","region-code":"US-NC","continente":"NA"},
{"id":758,"Nombre":"Brownsville South Padre Island International Airport","code":"BRO","region-code":"US-TX","continente":"NA"},
{"id":759,"Nombre":"Sir Seewoosagur Ramgoolam International Airport","code":"MRU","region-code":"MU-GP","continente":"AF"},
{"id":760,"Nombre":"Nelspruit Airport","code":"NLP","region-code":"ZA-MP","continente":"AF"},
{"id":761,"Nombre":"Eliye Springs Airport","code":"EYS","region-code":"KE-700","continente":"AF"},
{"id":762,"Nombre":"San Juan Aposento Airport","code":"APE","region-code":"PE-ICA","continente":"SA"},
{"id":763,"Nombre":"Brampton Island Airport","code":"BMP","region-code":"AU-QLD","continente":"OC"},
{"id":764,"Nombre":"Menara Airport","code":"RAK","region-code":"MA-MAR","continente":"AF"},
{"id":765,"Nombre":"Donoi Airport","code":"ULZ","region-code":"MN-057","continente":"AS"},
{"id":766,"Nombre":"Brest Airport","code":"BQT","region-code":"BY-BR","continente":"EU"},
{"id":767,"Nombre":"St. Mary's County Regional Airport","code":"LTW","region-code":"US-MD","continente":"NA"},
{"id":768,"Nombre":"Ashgabat International Airport","code":"ASB","region-code":"TM-A","continente":"AS"},
{"id":769,"Nombre":"Piloto Osvaldo Marques Dias Airport","code":"AFL","region-code":"BR-MT","continente":"SA"},
{"id":770,"Nombre":"Raivavae Airport","code":"RVV","region-code":"PF-U-A","continente":"OC"},
{"id":771,"Nombre":"Tarbes-Lourdes-Pyrénées Airport","code":"LDE","region-code":"FR-N","continente":"EU"},
{"id":772,"Nombre":"Constanza - Expedición 14 de Junio National Airport","code":"COZ","region-code":"DO-13","continente":"NA"},
{"id":773,"Nombre":"Wunnumin Lake Airport","code":"WNN","region-code":"CA-ON","continente":"NA"},
{"id":774,"Nombre":"Oro Negro Airport","code":"CBS","region-code":"VE-V","continente":"SA"},
{"id":775,"Nombre":"Kotabangun Airport","code":"KOD","region-code":"ID-KI","continente":"AS"},
{"id":776,"Nombre":"Limon International Airport","code":"LIO","region-code":"CR-L","continente":"NA"},
{"id":777,"Nombre":"Wabush Airport","code":"YWK","region-code":"CA-NL","continente":"NA"},
{"id":778,"Nombre":"Evelio Javier Airport","code":"EUQ","region-code":"PH-ANT","continente":"AS"},
{"id":779,"Nombre":"Charlottetown Airport","code":"YYG","region-code":"CA-PE","continente":"NA"},
{"id":780,"Nombre":"Melchor de Mencos Airport","code":"MCR","region-code":"GT-PE","continente":"NA"},
{"id":781,"Nombre":"Milos Airport","code":"MLO","region-code":"GR-82","continente":"EU"},
{"id":782,"Nombre":"Baillif Airport","code":"BBR","region-code":"GP-U-A","continente":"NA"},
{"id":783,"Nombre":"Maple Bay Seaplane Base","code":"YAQ","region-code":"CA-BC","continente":"NA"},
{"id":784,"Nombre":"Wrangell Airport","code":"WRG","region-code":"US-AK","continente":"NA"},
{"id":785,"Nombre":"Natuashish Airport","code":"YNP","region-code":"CA-NL","continente":"NA"},
{"id":786,"Nombre":"Lunyuk Airport","code":"LYK","region-code":"ID-NB","continente":"AS"},
{"id":787,"Nombre":"Nakhon Si Thammarat Airport","code":"NST","region-code":"TH-80","continente":"AS"},
{"id":788,"Nombre":"Newcastle Airport","code":"NCS","region-code":"ZA-NL","continente":"AF"},
{"id":789,"Nombre":"Animas Air Park","code":"AMK","region-code":"US-CO","continente":"NA"},
{"id":790,"Nombre":"Puerto Escondido International Airport","code":"PXM","region-code":"MX-OAX","continente":"NA"},
{"id":791,"Nombre":"Mumias Airport","code":"MUM","region-code":"KE-900","continente":"AF"},
{"id":792,"Nombre":"General José María Yáñez International Airport","code":"GYM","region-code":"MX-SON","continente":"NA"},
{"id":793,"Nombre":"Edmond Cané Airport","code":"IOU","region-code":"NC-U-A","continente":"OC"},
{"id":794,"Nombre":"Wakunai Airport","code":"WKN","region-code":"PG-EBR","continente":"OC"},
{"id":795,"Nombre":"Gisborne Airport","code":"GIS","region-code":"NZ-GIS","continente":"OC"},
{"id":796,"Nombre":"Lowe AHP (Fort Rucker) Heliport","code":"LOR","region-code":"US-AL","continente":"NA"},
{"id":797,"Nombre":"Colon Airport","code":"MRJ","region-code":"HN-LP","continente":"NA"},
{"id":798,"Nombre":"Danilo Atienza Air Base","code":"SGL","region-code":"PH-CAV","continente":"AS"},
{"id":799,"Nombre":"Rawalakot Airport","code":"RAZ","region-code":"PK-JK","continente":"AS"},
{"id":800,"Nombre":"Rock Hill - York County Airport","code":"RKH","region-code":"US-SC","continente":"NA"},
{"id":801,"Nombre":"Schenck Field","code":"ICL","region-code":"US-IA","continente":"NA"},
{"id":802,"Nombre":"Nauru International Airport","code":"INU","region-code":"NR-14","continente":"OC"},
{"id":803,"Nombre":"King Salman Abdulaziz Airport","code":"DWD","region-code":"SA-01","continente":"AS"},
{"id":804,"Nombre":"Gbadolite Airport","code":"BDT","region-code":"CD-EQ","continente":"AF"},
{"id":805,"Nombre":"Grand Bahama International Airport","code":"FPO","region-code":"BS-FP","continente":"NA"},
{"id":806,"Nombre":"Lonorore Airport","code":"LNE","region-code":"VU-PAM","continente":"OC"},
{"id":807,"Nombre":"Courtenay Airpark","code":"YCA","region-code":"CA-BC","continente":"NA"},
{"id":808,"Nombre":"Lowcountry Regional Airport","code":"RBW","region-code":"US-SC","continente":"NA"},
{"id":809,"Nombre":"Clyde River Airport","code":"YCY","region-code":"CA-NU","continente":"NA"},
{"id":810,"Nombre":"San Jose Airport","code":"SJI","region-code":"PH-MDC","continente":"AS"},
{"id":811,"Nombre":"Dyess Air Force Base","code":"DYS","region-code":"US-TX","continente":"NA"},
{"id":812,"Nombre":"Bol Airport","code":"BWK","region-code":"HR-17","continente":"EU"},
{"id":813,"Nombre":"Pincher Creek Airport","code":"WPC","region-code":"CA-AB","continente":"NA"},
{"id":814,"Nombre":"King Island Airport","code":"KNS","region-code":"AU-TAS","continente":"OC"},
{"id":815,"Nombre":"Kashechewan Airport","code":"ZKE","region-code":"CA-ON","continente":"NA"},
{"id":816,"Nombre":"Cape Lisburne LRRS Airport","code":"LUR","region-code":"US-AK","continente":"NA"},
{"id":817,"Nombre":"Massena International Richards Field","code":"MSS","region-code":"US-NY","continente":"NA"},
{"id":818,"Nombre":"Amílcar Cabral International Airport","code":"SID","region-code":"CV-B","continente":"AF"},
{"id":819,"Nombre":"Grant Co Regional/Ogilvie Field","code":"JDA","region-code":"US-OR","continente":"NA"},
{"id":820,"Nombre":"Sim Airport","code":"SMJ","region-code":"PG-MPL","continente":"OC"},
{"id":821,"Nombre":"Matari Airport","code":"IRP","region-code":"CD-OR","continente":"AF"},
{"id":822,"Nombre":"La Môle Airport","code":"LTT","region-code":"FR-U","continente":"EU"},
{"id":823,"Nombre":"Roscoe Turner Airport","code":"CRX","region-code":"US-MS","continente":"NA"},
{"id":824,"Nombre":"Edinburgh Airport","code":"EDI","region-code":"GB-SCT","continente":"EU"},
{"id":825,"Nombre":"Muanda Airport","code":"MNB","region-code":"CD-BC","continente":"AF"},
{"id":826,"Nombre":"Tokushima Airport/JMSDF Air Base","code":"TKS","region-code":"JP-36","continente":"AS"},
{"id":827,"Nombre":"Le Havre Octeville Airport","code":"LEH","region-code":"FR-Q","continente":"EU"},
{"id":828,"Nombre":"Big Creek Airport","code":"BGK","region-code":"BZ-SC","continente":"NA"},
{"id":829,"Nombre":"Crested Butte Airpark","code":"CSE","region-code":"US-CO","continente":"NA"},
{"id":830,"Nombre":"Iringa Airport","code":"IRI","region-code":"TZ-04","continente":"AF"},
{"id":831,"Nombre":"Perry Municipal Airport","code":"PRO","region-code":"US-IA","continente":"NA"},
{"id":832,"Nombre":"Gelephu Airport","code":"GLU","region-code":"BT-31","continente":"AS"},
{"id":833,"Nombre":"Lockhart River Airport","code":"IRG","region-code":"AU-QLD","continente":"OC"},
{"id":834,"Nombre":"Tarapoa Airport","code":"TPC","region-code":"EC-U","continente":"SA"},
{"id":835,"Nombre":"Kuini Lavenia Airport","code":"NTT","region-code":"TO-03","continente":"OC"},
{"id":836,"Nombre":"Wells Municipal Airport/Harriet Field","code":"LWL","region-code":"US-NV","continente":"NA"},
{"id":837,"Nombre":"Erfurt Airport","code":"ERF","region-code":"DE-TH","continente":"EU"},
{"id":838,"Nombre":"Congonhas Airport","code":"CGH","region-code":"BR-SP","continente":"SA"},
{"id":839,"Nombre":"Jessore Airport","code":"JSR","region-code":"BD-4","continente":"AS"},
{"id":840,"Nombre":"Carbon County Regional/Buck Davis Field","code":"PUC","region-code":"US-UT","continente":"NA"},
{"id":841,"Nombre":"Al Udeid Air Base","code":"XJD","region-code":"QA-RA","continente":"AS"},
{"id":842,"Nombre":"Cherepovets Airport","code":"CEE","region-code":"RU-VLG","continente":"EU"},
{"id":843,"Nombre":"Srednekolymsk Airport","code":"SEK","region-code":"RU-SA","continente":"EU"},
{"id":844,"Nombre":"Chimoio Airport","code":"VPY","region-code":"MZ-B","continente":"AF"},
{"id":845,"Nombre":"Fort St John Airport","code":"YXJ","region-code":"CA-BC","continente":"NA"},
{"id":846,"Nombre":"Kapalua Airport","code":"JHM","region-code":"US-HI","continente":"NA"},
{"id":847,"Nombre":"Preah Vinhear Airport","code":"OMY","region-code":"KH-13","continente":"AS"},
{"id":848,"Nombre":"Yeager Airport","code":"CRW","region-code":"US-WV","continente":"NA"},
{"id":849,"Nombre":"Ocala International Airport - Jim Taylor Field","code":"OCF","region-code":"US-FL","continente":"NA"},
{"id":850,"Nombre":"Coromandel Aerodrome","code":"CMV","region-code":"NZ-WKO","continente":"OC"},
{"id":851,"Nombre":"York Landing Airport","code":"ZAC","region-code":"CA-MB","continente":"NA"},
{"id":852,"Nombre":"Alpha Airport","code":"ABH","region-code":"AU-QLD","continente":"OC"},
{"id":853,"Nombre":"Sacramento International Airport","code":"SMF","region-code":"US-CA","continente":"NA"},
{"id":854,"Nombre":"Grantsburg Municipal Airport","code":"GTG","region-code":"US-WI","continente":"NA"},
{"id":855,"Nombre":"Budapest Liszt Ferenc International Airport","code":"BUD","region-code":"HU-PE","continente":"EU"},
{"id":856,"Nombre":"Tikchik Lodge Seaplane Base","code":"KTH","region-code":"US-AK","continente":"NA"},
{"id":857,"Nombre":"Temindung Airport","code":"SRI","region-code":"ID-KI","continente":"AS"},
{"id":858,"Nombre":"Sembach Air Base","code":"SEX","region-code":"DE-RP","continente":"EU"},
{"id":859,"Nombre":"Jiagedaqi Airport","code":"JGD","region-code":"CN-23","continente":"AS"},
{"id":860,"Nombre":"Fazenda São Francisco do Itaquerê Airport","code":"0","region-code":"BR-SP","continente":"SA"},
{"id":861,"Nombre":"New Ulm Municipal Airport","code":"ULM","region-code":"US-MN","continente":"NA"},
{"id":862,"Nombre":"Devonport Airport","code":"DPO","region-code":"AU-TAS","continente":"OC"},
{"id":863,"Nombre":"Ağrı Airport","code":"AJI","region-code":"TR-04","continente":"AS"},
{"id":864,"Nombre":"New York Skyports Inc Seaplane Base","code":"QNY","region-code":"US-NY","continente":"NA"},
{"id":865,"Nombre":"Vanguardia Airport","code":"VVC","region-code":"CO-MET","continente":"SA"},
{"id":866,"Nombre":"Ialibu Airport","code":"IAL","region-code":"PG-SHM","continente":"OC"},
{"id":867,"Nombre":"Altiport L'Alpe d'Huez - Henri GIRAUD","code":"AHZ","region-code":"FR-V","continente":"EU"},
{"id":868,"Nombre":"Iamalele Airport","code":"IMA","region-code":"PG-MBA","continente":"OC"},
{"id":869,"Nombre":"Siirt Airport","code":"SXZ","region-code":"TR-56","continente":"AS"},
{"id":870,"Nombre":"Nome Airport","code":"OME","region-code":"US-AK","continente":"NA"},
{"id":871,"Nombre":"Grand Central Airport","code":"GCJ","region-code":"ZA-GT","continente":"AF"},
{"id":872,"Nombre":"Gunnison Crested Butte Regional Airport","code":"GUC","region-code":"US-CO","continente":"NA"},
{"id":873,"Nombre":"Transilvania Târgu Mureş International Airport","code":"TGM","region-code":"RO-MS","continente":"EU"},
{"id":874,"Nombre":"Sabu-Tardanu Airport","code":"SAU","region-code":"ID-NT","continente":"AS"},
{"id":875,"Nombre":"Dimmit County Airport","code":"CZT","region-code":"US-TX","continente":"NA"},
{"id":876,"Nombre":"Dalgaranga Gold Mine Airport","code":"DGD","region-code":"AU-WA","continente":"OC"},
{"id":877,"Nombre":"Okayama Airport","code":"OKJ","region-code":"JP-33","continente":"AS"},
{"id":878,"Nombre":"Ottawa / Rockcliffe Airport","code":"YRO","region-code":"CA-ON","continente":"NA"},
{"id":879,"Nombre":"Karlsruhe Baden-Baden Airport","code":"FKB","region-code":"DE-BW","continente":"EU"},
{"id":880,"Nombre":"Uttaradit Airport","code":"UTR","region-code":"TH-53","continente":"AS"},
{"id":881,"Nombre":"Luena Airport","code":"LUO","region-code":"AO-MOX","continente":"AF"},
{"id":882,"Nombre":"Albacete-Los Llanos Airport","code":"ABC","region-code":"ES-CM","continente":"EU"},
{"id":883,"Nombre":"Etimesgut Air Base","code":"ANK","region-code":"TR-06","continente":"AS"},
{"id":884,"Nombre":"Konawaruk Airport","code":"KKG","region-code":"GY-PT","continente":"SA"},
{"id":885,"Nombre":"Bay City Municipal Airport","code":"BBC","region-code":"US-TX","continente":"NA"},
{"id":886,"Nombre":"Playa del Carmen Airport","code":"PCM","region-code":"MX-ROO","continente":"NA"},
{"id":887,"Nombre":"Manila Municipal Airport","code":"MXA","region-code":"US-AR","continente":"NA"},
{"id":888,"Nombre":"Kostanay West Airport","code":"KSN","region-code":"KZ-KUS","continente":"AS"},
{"id":889,"Nombre":"Ewo Airport","code":"EWO","region-code":"CG-8","continente":"AF"},
{"id":890,"Nombre":"Mandora Airport","code":"MQA","region-code":"AU-WA","continente":"OC"},
{"id":891,"Nombre":"Tok Junction Airport","code":"TKJ","region-code":"US-AK","continente":"NA"},
{"id":892,"Nombre":"Stephenville Airport","code":"YJT","region-code":"CA-NL","continente":"NA"},
{"id":893,"Nombre":"Santa Ana Airport","code":"CRC","region-code":"CO-VAC","continente":"SA"},
{"id":894,"Nombre":"Larnaca International Airport","code":"LCA","region-code":"CY-04","continente":"AS"},
{"id":895,"Nombre":"Silver Plains Airport","code":"SSP","region-code":"AU-QLD","continente":"OC"},
{"id":896,"Nombre":"Enfidha - Hammamet International Airport","code":"NBE","region-code":"TN-51","continente":"AF"},
{"id":897,"Nombre":"TSTC Waco Airport","code":"CNW","region-code":"US-TX","continente":"NA"},
{"id":898,"Nombre":"Kericho Airport","code":"KEY","region-code":"KE-700","continente":"AF"},
{"id":899,"Nombre":"Rome State Airport","code":"REO","region-code":"US-OR","continente":"NA"},
{"id":900,"Nombre":"Mayor PNP Nancy Flores Paucar Airport","code":"MZA","region-code":"PE-JUN","continente":"SA"},
{"id":901,"Nombre":"Charleston Air Force Base-International Airport","code":"CHS","region-code":"US-SC","continente":"NA"},
{"id":902,"Nombre":"Wanaka Airport","code":"WKA","region-code":"NZ-OTA","continente":"OC"},
{"id":903,"Nombre":"Hughes Airport","code":"HUS","region-code":"US-AK","continente":"NA"},
{"id":904,"Nombre":"General Santos International Airport","code":"GES","region-code":"PH-SCO","continente":"AS"},
{"id":905,"Nombre":"Xishuangbanna Gasa Airport","code":"JHG","region-code":"CN-53","continente":"AS"},
{"id":906,"Nombre":"Margaret Ekpo International Airport","code":"CBQ","region-code":"NG-CR","continente":"AF"},
{"id":907,"Nombre":"Felker Army Air Field","code":"FAF","region-code":"US-VA","continente":"NA"},
{"id":908,"Nombre":"Menara Airport","code":"RAK","region-code":"MA-MAR","continente":"AF"},
{"id":909,"Nombre":"Cherkasy International Airport","code":"CKC","region-code":"UA-71","continente":"EU"},
{"id":910,"Nombre":"Pau Pyrénées Airport","code":"PUF","region-code":"FR-B","continente":"EU"},
{"id":911,"Nombre":"Frégate Island Airport","code":"FRK","region-code":"SC-15","continente":"AF"},
{"id":912,"Nombre":"Rapid City Regional Airport","code":"RAP","region-code":"US-SD","continente":"NA"},
{"id":913,"Nombre":"French Valley Airport","code":"RBK","region-code":"US-CA","continente":"NA"},
{"id":914,"Nombre":"Aramac Airport","code":"AXC","region-code":"AU-QLD","continente":"OC"},
{"id":915,"Nombre":"Hechi Jinchengjiang Airport","code":"HCJ","region-code":"CN-45","continente":"AS"},
{"id":916,"Nombre":"Ie Jima Airport","code":"IEJ","region-code":"JP-47","continente":"AS"},
{"id":917,"Nombre":"Alferez FAP Alfredo Vladimir Sara Bauer Airport","code":"AOP","region-code":"PE-LOR","continente":"SA"},
{"id":918,"Nombre":"Park Township Airport","code":"HLM","region-code":"US-MI","continente":"NA"},
{"id":919,"Nombre":"Sindhri Tharparkar Airport","code":"MPD","region-code":"PK-SD","continente":"AS"},
{"id":920,"Nombre":"Laurie River Airport","code":"LRQ","region-code":"CA-MB","continente":"NA"},
{"id":921,"Nombre":"Kerama Airport","code":"KJP","region-code":"JP-47","continente":"AS"},
{"id":922,"Nombre":"Kalumburu Airport","code":"UBU","region-code":"AU-WA","continente":"OC"},
{"id":923,"Nombre":"London Luton Airport","code":"LTN","region-code":"GB-ENG","continente":"EU"},
{"id":924,"Nombre":"Woodie Woodie Airport","code":"WWI","region-code":"AU-WA","continente":"OC"},
{"id":925,"Nombre":"Orsk Airport","code":"OSW","region-code":"RU-ORE","continente":"EU"},
{"id":926,"Nombre":"Drysdale River Airport","code":"DRY","region-code":"AU-WA","continente":"OC"},
{"id":927,"Nombre":"Bahrain International Airport","code":"BAH","region-code":"BH-15","continente":"AS"},
{"id":928,"Nombre":"Dajarra Airport","code":"DJR","region-code":"AU-QLD","continente":"OC"},
{"id":929,"Nombre":"Rennell/Tingoa Airport","code":"RNL","region-code":"SB-RB","continente":"OC"},
{"id":930,"Nombre":"Kambuaya Airport","code":"KBX","region-code":"ID-PB","continente":"AS"},
{"id":931,"Nombre":"Kotlas Airport","code":"KSZ","region-code":"RU-ARK","continente":"EU"},
{"id":932,"Nombre":"Battle Mountain Airport","code":"BAM","region-code":"US-NV","continente":"NA"},
{"id":933,"Nombre":"Tinker Air Force Base","code":"TIK","region-code":"US-OK","continente":"NA"},
{"id":934,"Nombre":"Oban Airport","code":"OBN","region-code":"GB-SCT","continente":"EU"},
{"id":935,"Nombre":"Mapoda Airport","code":"MPF","region-code":"PG-WPD","continente":"OC"},
{"id":936,"Nombre":"Yangzhou Taizhou Airport","code":"YTY","region-code":"CN-32","continente":"AS"},
{"id":937,"Nombre":"Chile Chico Airport","code":"CCH","region-code":"CL-AI","continente":"SA"},
{"id":938,"Nombre":"Tuguegarao Airport","code":"TUG","region-code":"PH-CAG","continente":"AS"},
{"id":939,"Nombre":"Tajima Airport","code":"TJH","region-code":"JP-28","continente":"AS"},
{"id":940,"Nombre":"General Mariano Escobedo International Airport","code":"MTY","region-code":"MX-NLE","continente":"NA"},
{"id":941,"Nombre":"Rivière-du-Loup Airport","code":"YRI","region-code":"CA-QC","continente":"NA"},
{"id":942,"Nombre":"Fort Lauderdale Hollywood International Airport","code":"FLL","region-code":"US-FL","continente":"NA"},
{"id":943,"Nombre":"Xingtai Dalian Airport","code":"XNT","region-code":"CN-13","continente":"AS"},
{"id":944,"Nombre":"Kristiansund Airport (Kvernberget)","code":"KSU","region-code":"NO-15","continente":"EU"},
{"id":945,"Nombre":"Jersey Airport","code":"JER","region-code":"JE-U-A","continente":"EU"},
{"id":946,"Nombre":"Napa County Airport","code":"APC","region-code":"US-CA","continente":"NA"},
{"id":947,"Nombre":"Aarhus Airport","code":"AAR","region-code":"DK-82","continente":"EU"},
{"id":948,"Nombre":"Lianshui Airport","code":"HIA","region-code":"CN-32","continente":"AS"},
{"id":949,"Nombre":"Drummond Island Airport","code":"DRE","region-code":"US-MI","continente":"NA"},
{"id":950,"Nombre":"Hayman Island Resort Seaplane Base","code":"HIS","region-code":"AU-QLD","continente":"OC"},
{"id":951,"Nombre":"Mar de Cortés International Airport","code":"PPE","region-code":"MX-SON","continente":"NA"},
{"id":952,"Nombre":"Lahr Airport","code":"LHA","region-code":"DE-BW","continente":"EU"},
{"id":953,"Nombre":"Beloyarskiy Airport","code":"EYK","region-code":"RU-KHM","continente":"EU"},
{"id":954,"Nombre":"Wagny Airport","code":"WGY","region-code":"GA-7","continente":"AF"},
{"id":955,"Nombre":"Usino Airport","code":"USO","region-code":"PG-MPM","continente":"OC"},
{"id":956,"Nombre":"Francisco B. Reyes Airport","code":"USU","region-code":"PH-PLW","continente":"AS"},
{"id":957,"Nombre":"East Texas Regional Airport","code":"GGG","region-code":"US-TX","continente":"NA"},
{"id":958,"Nombre":"Caiguna Airport","code":"CGV","region-code":"AU-WA","continente":"OC"},
{"id":959,"Nombre":"Arak Airport","code":"AJK","region-code":"IR-22","continente":"AS"},
{"id":960,"Nombre":"Sulayel Airport","code":"SLF","region-code":"SA-01","continente":"AS"},
{"id":961,"Nombre":"Wittenoom Airport","code":"WIT","region-code":"AU-WA","continente":"OC"},
{"id":962,"Nombre":"Ruhengeri Airport","code":"RHG","region-code":"RW-03","continente":"AF"},
{"id":963,"Nombre":"Nyeri Airport","code":"NYE","region-code":"KE-200","continente":"AF"},
{"id":964,"Nombre":"Roswell International Air Center Airport","code":"ROW","region-code":"US-NM","continente":"NA"},
{"id":965,"Nombre":"Xiamen Gaoqi International Airport","code":"XMN","region-code":"CN-35","continente":"AS"},
{"id":966,"Nombre":"Zakuoma Airport","code":"AKM","region-code":"TD-SA","continente":"AF"},
{"id":967,"Nombre":"Puerto Barrios Airport","code":"PBR","region-code":"GT-IZ","continente":"NA"},
{"id":968,"Nombre":"Sardar Vallabhbhai Patel International Airport","code":"AMD","region-code":"IN-GJ","continente":"AS"},
{"id":969,"Nombre":"Burao Airport","code":"BUO","region-code":"SO-TO","continente":"AF"},
{"id":970,"Nombre":"Yedinka Airport","code":"EDN","region-code":"RU-PRI","continente":"EU"},
{"id":971,"Nombre":"Cecil Airport","code":"VQQ","region-code":"US-FL","continente":"NA"},
{"id":972,"Nombre":"Ngot Nzoungou Airport","code":"DIS","region-code":"CG-9","continente":"AF"},
{"id":973,"Nombre":"Kiruna Airport","code":"KRN","region-code":"SE-BD","continente":"EU"},
{"id":974,"Nombre":"Lightning Ridge Airport","code":"LHG","region-code":"AU-NSW","continente":"OC"},
{"id":975,"Nombre":"Sultan Abdul Aziz Shah International Airport","code":"SZB","region-code":"MY-10","continente":"AS"},
{"id":976,"Nombre":"Quakertown Airport","code":"UKT","region-code":"US-PA","continente":"NA"},
{"id":977,"Nombre":"Suboficial Ay Santiago Germano Airport","code":"AFA","region-code":"AR-M","continente":"SA"},
{"id":978,"Nombre":"Salerno Landing Zone Airport","code":"OLR","region-code":"AF-PIA","continente":"AS"},
{"id":979,"Nombre":"Texada Gillies Bay Airport","code":"YGB","region-code":"CA-BC","continente":"NA"},
{"id":980,"Nombre":"Altus Quartz Mountain Regional Airport","code":"AXS","region-code":"US-OK","continente":"NA"},
{"id":981,"Nombre":"Porto Amboim Airport","code":"PBN","region-code":"AO-CUS","continente":"AF"},
{"id":982,"Nombre":"Currillo Airport","code":"CUI","region-code":"CO-CAS","continente":"SA"},
{"id":983,"Nombre":"General Francisco J. Mujica International Airport","code":"MLM","region-code":"MX-MIC","continente":"NA"},
{"id":984,"Nombre":"Warracknabeal Airport","code":"WKB","region-code":"AU-VIC","continente":"OC"},
{"id":985,"Nombre":"Cox Field","code":"PRX","region-code":"US-TX","continente":"NA"},
{"id":986,"Nombre":"Pardubice Airport","code":"PED","region-code":"CZ-PA","continente":"EU"},
{"id":987,"Nombre":"Puerto Leda Airport","code":"PBT","region-code":"PY-16","continente":"SA"},
{"id":988,"Nombre":"Miyazaki Airport","code":"KMI","region-code":"JP-45","continente":"AS"},
{"id":989,"Nombre":"Ingjaldssanður Airport","code":"HLO","region-code":"IS-4","continente":"EU"},
{"id":990,"Nombre":"Calexico International Airport","code":"CXL","region-code":"US-CA","continente":"NA"},
{"id":991,"Nombre":"Marakei Airport","code":"MZK","region-code":"KI-G","continente":"OC"},
{"id":992,"Nombre":"Moose Jaw Air Vice Marshal C. M. McEwen Airport","code":"YMJ","region-code":"CA-SK","continente":"NA"},
{"id":993,"Nombre":"Togiak Airport","code":"TOG","region-code":"US-AK","continente":"NA"},
{"id":994,"Nombre":"Mildura Airport","code":"MQL","region-code":"AU-VIC","continente":"OC"},
{"id":995,"Nombre":"Betou Airport","code":"BTB","region-code":"CG-7","continente":"AF"},
{"id":996,"Nombre":"Ayawasi Airport","code":"AYW","region-code":"ID-PB","continente":"AS"},
{"id":997,"Nombre":"Mudgee Airport","code":"DGE","region-code":"AU-NSW","continente":"OC"},
{"id":998,"Nombre":"Sulphur Springs Municipal Airport","code":"SLR","region-code":"US-TX","continente":"NA"},
{"id":999,"Nombre":"Al Dhafra Air Base","code":"DHF","region-code":"AE-AZ","continente":"AS"},
{"id":1000,"Nombre":"Kununurra Airport","code":"KNX","region-code":"AU-WA","continente":"OC"}]